{"forecastHours": [{"interval": {"startTime": "2026-04-05T21:00:00Z", "endTime": "2026-04-05T22:00:00Z"}, "displayDateTime": {"year": 2026, "month": 4, "day": 5, "hours": 23, "minutes": 0, "seconds": 0, "nanos": 0, "utcOffset": "7200s"}, "weatherCondition": {"iconBaseUri": "https://maps.gstatic.com/weather/v1/cloudy", "description": {"text": "Cloudy", "languageCode": "en"}, "type": "CLOUDY"}, "temperature": {"unit": "CELSIUS", "degrees": 12}, "feelsLikeTemperature": {"unit": "CELSIUS", "degrees": 12}, "dewPoint": {"unit": "CELSIUS", "degrees": 9.8}, "heatIndex": {"unit": "CELSIUS", "degrees": 12}, "windChill": {"unit": "CELSIUS", "degrees": 12}, "wetBulbTemperature": {"unit": "CELSIUS", "degrees": 10.7}, "precipitation": {"probability": {"type": "RAIN", "percent": 10}, "snowQpf": {"unit": "MILLIMETERS", "quantity": 0}, "qpf": {"unit": "MILLIMETERS", "quantity": 0}}, "airPressure": {"meanSeaLevelMillibars": 1026.15}, "wind": {"direction": {"cardinal": "NORTH_NORTHEAST", "degrees": 16}, "speed": {"unit": "KILOMETERS_PER_HOUR", "value": 5}, "gust": {"unit": "KILOMETERS_PER_HOUR", "value": 10}}, "visibility": {"unit": "KILOMETERS", "distance": 16}, "iceThickness": {"unit": "MILLIMETERS", "thickness": 0}, "isDaytime": false, "relativeHumidity": 86, "uvIndex": 0, "thunderstormProbability": 0, "cloudCover": 99}, {"interval": {"startTime": "2026-04-05T22:00:00Z", "endTime": "2026-04-05T23:00:00Z"}, "displayDateTime": {"year": 2026, "month": 4, "day": 6, "hours": 0, "minutes": 0, "seconds": 0, "nanos": 0, "utcOffset": "7200s"}, "weatherCondition": {"iconBaseUri": "https://maps.gstatic.com/weather/v1/mostly_cloudy_night", "description": {"text": "Mostly cloudy", "languageCode": "en"}, "type": "MOSTLY_CLOUDY"}, "temperature": {"unit": "CELSIUS", "degrees": 11.1}, "feelsLikeTemperature": {"unit": "CELSIUS", "degrees": 11.1}, "dewPoint": {"unit": "CELSIUS", "degrees": 9.5}, "heatIndex": {"unit": "CELSIUS", "degrees": 11.1}, "windChill": {"unit": "CELSIUS", "degrees": 11.1}, "wetBulbTemperature": {"unit": "CELSIUS", "degrees": 10.2}, "precipitation": {"probability": {"type": "RAIN", "percent": 10}, "snowQpf": {"unit": "MILLIMETERS", "quantity": 0}, "qpf": {"unit": "MILLIMETERS", "quantity": 0}}, "airPressure": {"meanSeaLevelMillibars": 1026.73}, "wind": {"direction": {"cardinal": "NORTH_NORTHEAST", "degrees": 25}, "speed": {"unit": "KILOMETERS_PER_HOUR", "value": 5}, "gust": {"unit": "KILOMETERS_PER_HOUR", "value": 6}}, "visibility": {"unit": "KILOMETERS", "distance": 16}, "iceThickness": {"unit": "MILLIMETERS", "thickness": 0}, "isDaytime": false, "relativeHumidity": 90, "uvIndex": 0, "thunderstormProbability": 0, "cloudCover": 88}, {"interval": {"startTime": "2026-04-05T23:00:00Z", "endTime": "2026-04-06T00:00:00Z"}, "displayDateTime": {"year": 2026, "month": 4, "day": 6, "hours": 1, "minutes": 0, "seconds": 0, "nanos": 0, "utcOffset": "7200s"}, "weatherCondition": {"iconBaseUri": "https://maps.gstatic.com/weather/v1/partly_clear", "description": {"text": "Partly cloudy", "languageCode": "en"}, "type": "PARTLY_CLOUDY"}, "temperature": {"unit": "CELSIUS", "degrees": 10.2}, "feelsLikeTemperature": {"unit": "CELSIUS", "degrees": 10}, "dewPoint": {"unit": "CELSIUS", "degrees": 9.1}, "heatIndex": {"unit": "CELSIUS", "degrees": 10.2}, "windChill": {"unit": "CELSIUS", "degrees": 10}, "wetBulbTemperature": {"unit": "CELSIUS", "degrees": 9.6}, "precipitation": {"probability": {"type": "RAIN", "percent": 5}, "snowQpf": {"unit": "MILLIMETERS", "quantity": 0}, "qpf": {"unit": "MILLIMETERS", "quantity": 0}}, "airPressure": {"meanSeaLevelMillibars": 1027.13}, "wind": {"direction": {"cardinal": "NORTH", "degrees": 3}, "speed": {"unit": "KILOMETERS_PER_HOUR", "value": 5}, "gust": {"unit": "KILOMETERS_PER_HOUR", "value": 6}}, "visibility": {"unit": "KILOMETERS", "distance": 13}, "iceThickness": {"unit": "MILLIMETERS", "thickness": 0}, "isDaytime": false, "relativeHumidity": 93, "uvIndex": 0, "thunderstormProbability": 0, "cloudCover": 49}, {"interval": {"startTime": "2026-04-06T00:00:00Z", "endTime": "2026-04-06T01:00:00Z"}, "displayDateTime": {"year": 2026, "month": 4, "day": 6, "hours": 2, "minutes": 0, "seconds": 0, "nanos": 0, "utcOffset": "7200s"}, "weatherCondition": {"iconBaseUri": "https://maps.gstatic.com/weather/v1/clear", "description": {"text": "Clear", "languageCode": "en"}, "type": "CLEAR"}, "temperature": {"unit": "CELSIUS", "degrees": 9.8}, "feelsLikeTemperature": {"unit": "CELSIUS", "degrees": 9}, "dewPoint": {"unit": "CELSIUS", "degrees": 8.7}, "heatIndex": {"unit": "CELSIUS", "degrees": 9.8}, "windChill": {"unit": "CELSIUS", "degrees": 9}, "wetBulbTemperature": {"unit": "CELSIUS", "degrees": 9.2}, "precipitation": {"probability": {"type": "RAIN", "percent": 0}, "snowQpf": {"unit": "MILLIMETERS", "quantity": 0}, "qpf": {"unit": "MILLIMETERS", "quantity": 0}}, "airPressure": {"meanSeaLevelMillibars": 1026.81}, "wind": {"direction": {"cardinal": "NORTH", "degrees": 8}, "speed": {"unit": "KILOMETERS_PER_HOUR", "value": 6}, "gust": {"unit": "KILOMETERS_PER_HOUR", "value": 10}}, "visibility": {"unit": "KILOMETERS", "distance": 13}, "iceThickness": {"unit": "MILLIMETERS", "thickness": 0}, "isDaytime": false, "relativeHumidity": 92, "uvIndex": 0, "thunderstormProbability": 0, "cloudCover": 9}, {"interval": {"startTime": "2026-04-06T01:00:00Z", "endTime": "2026-04-06T02:00:00Z"}, "displayDateTime": {"year": 2026, "month": 4, "day": 6, "hours": 3, "minutes": 0, "seconds": 0, "nanos": 0, "utcOffset": "7200s"}, "weatherCondition": {"iconBaseUri": "https://maps.gstatic.com/weather/v1/clear", "description": {"text": "Clear", "languageCode": "en"}, "type": "CLEAR"}, "temperature": {"unit": "CELSIUS", "degrees": 9.2}, "feelsLikeTemperature": {"unit": "CELSIUS", "degrees": 8}, "dewPoint": {"unit": "CELSIUS", "degrees": 8.1}, "heatIndex": {"unit": "CELSIUS", "degrees": 9.2}, "windChill": {"unit": "CELSIUS", "degrees": 8}, "wetBulbTemperature": {"unit": "CELSIUS", "degrees": 8.7}, "precipitation": {"probability": {"type": "RAIN", "percent": 0}, "snowQpf": {"unit": "MILLIMETERS", "quantity": 0}, "qpf": {"unit": "MILLIMETERS", "quantity": 0}}, "airPressure": {"meanSeaLevelMillibars": 1027.12}, "wind": {"direction": {"cardinal": "NORTH_NORTHEAST", "degrees": 15}, "speed": {"unit": "KILOMETERS_PER_HOUR", "value": 8}, "gust": {"unit": "KILOMETERS_PER_HOUR", "value": 11}}, "visibility": {"unit": "KILOMETERS", "distance": 13}, "iceThickness": {"unit": "MILLIMETERS", "thickness": 0}, "isDaytime": false, "relativeHumidity": 93, "uvIndex": 0, "thunderstormProbability": 0, "cloudCover": 6}, {"interval": {"startTime": "2026-04-06T02:00:00Z", "endTime": "2026-04-06T03:00:00Z"}, "displayDateTime": {"year": 2026, "month": 4, "day": 6, "hours": 4, "minutes": 0, "seconds": 0, "nanos": 0, "utcOffset": "7200s"}, "weatherCondition": {"iconBaseUri": "https://maps.gstatic.com/weather/v1/clear", "description": {"text": "Clear", "languageCode": "en"}, "type": "CLEAR"}, "temperature": {"unit": "CELSIUS", "degrees": 8.7}, "feelsLikeTemperature": {"unit": "CELSIUS", "degrees": 7}, "dewPoint": {"unit": "CELSIUS", "degrees": 7.6}, "heatIndex": {"unit": "CELSIUS", "degrees": 8.7}, "windChill": {"unit": "CELSIUS", "degrees": 7}, "wetBulbTemperature": {"unit": "CELSIUS", "degrees": 8.2}, "precipitation": {"probability": {"type": "RAIN", "percent": 0}, "snowQpf": {"unit": "MILLIMETERS", "quantity": 0}, "qpf": {"unit": "MILLIMETERS", "quantity": 0}}, "airPressure": {"meanSeaLevelMillibars": 1027.14}, "wind": {"direction": {"cardinal": "NORTH_NORTHEAST", "degrees": 20}, "speed": {"unit": "KILOMETERS_PER_HOUR", "value": 8}, "gust": {"unit": "KILOMETERS_PER_HOUR", "value": 16}}, "visibility": {"unit": "KILOMETERS", "distance": 13}, "iceThickness": {"unit": "MILLIMETERS", "thickness": 0}, "isDaytime": false, "relativeHumidity": 92, "uvIndex": 0, "thunderstormProbability": 0, "cloudCover": 2}, {"interval": {"startTime": "2026-04-06T03:00:00Z", "endTime": "2026-04-06T04:00:00Z"}, "displayDateTime": {"year": 2026, "month": 4, "day": 6, "hours": 5, "minutes": 0, "seconds": 0, "nanos": 0, "utcOffset": "7200s"}, "weatherCondition": {"iconBaseUri": "https://maps.gstatic.com/weather/v1/clear", "description": {"text": "Clear", "languageCode": "en"}, "type": "CLEAR"}, "temperature": {"unit": "CELSIUS", "degrees": 8.5}, "feelsLikeTemperature": {"unit": "CELSIUS", "degrees": 7}, "dewPoint": {"unit": "CELSIUS", "degrees": 7.2}, "heatIndex": {"unit": "CELSIUS", "degrees": 8.5}, "windChill": {"unit": "CELSIUS", "degrees": 7}, "wetBulbTemperature": {"unit": "CELSIUS", "degrees": 7.8}, "precipitation": {"probability": {"type": "RAIN", "percent": 0}, "snowQpf": {"unit": "MILLIMETERS", "quantity": 0}, "qpf": {"unit": "MILLIMETERS", "quantity": 0}}, "airPressure": {"meanSeaLevelMillibars": 1027.15}, "wind": {"direction": {"cardinal": "NORTH_NORTHEAST", "degrees": 23}, "speed": {"unit": "KILOMETERS_PER_HOUR", "value": 10}, "gust": {"unit": "KILOMETERS_PER_HOUR", "value": 13}}, "visibility": {"unit": "KILOMETERS", "distance": 14}, "iceThickness": {"unit": "MILLIMETERS", "thickness": 0}, "isDaytime": false, "relativeHumidity": 91, "uvIndex": 0, "thunderstormProbability": 0, "cloudCover": 0}, {"interval": {"startTime": "2026-04-06T04:00:00Z", "endTime": "2026-04-06T05:00:00Z"}, "displayDateTime": {"year": 2026, "month": 4, "day": 6, "hours": 6, "minutes": 0, "seconds": 0, "nanos": 0, "utcOffset": "7200s"}, "weatherCondition": {"iconBaseUri": "https://maps.gstatic.com/weather/v1/clear", "description": {"text": "Clear", "languageCode": "en"}, "type": "CLEAR"}, "temperature": {"unit": "CELSIUS", "degrees": 8.4}, "feelsLikeTemperature": {"unit": "CELSIUS", "degrees": 7}, "dewPoint": {"unit": "CELSIUS", "degrees": 7.1}, "heatIndex": {"unit": "CELSIUS", "degrees": 8.4}, "windChill": {"unit": "CELSIUS", "degrees": 7}, "wetBulbTemperature": {"unit": "CELSIUS", "degrees": 7.7}, "precipitation": {"probability": {"type": "RAIN", "percent": 0}, "snowQpf": {"unit": "MILLIMETERS", "quantity": 0}, "qpf": {"unit": "MILLIMETERS", "quantity": 0}}, "airPressure": {"meanSeaLevelMillibars": 1027.25}, "wind": {"direction": {"cardinal": "NORTH_NORTHEAST", "degrees": 21}, "speed": {"unit": "KILOMETERS_PER_HOUR", "value": 10}, "gust": {"unit": "KILOMETERS_PER_HOUR", "value": 13}}, "visibility": {"unit": "KILOMETERS", "distance": 14}, "iceThickness": {"unit": "MILLIMETERS", "thickness": 0}, "isDaytime": false, "relativeHumidity": 91, "uvIndex": 0, "thunderstormProbability": 0, "cloudCover": 5}, {"interval": {"startTime": "2026-04-06T05:00:00Z", "endTime": "2026-04-06T06:00:00Z"}, "displayDateTime": {"year": 2026, "month": 4, "day": 6, "hours": 7, "minutes": 0, "seconds": 0, "nanos": 0, "utcOffset": "7200s"}, "weatherCondition": {"iconBaseUri": "https://maps.gstatic.com/weather/v1/clear", "description": {"text": "Clear", "languageCode": "en"}, "type": "CLEAR"}, "temperature": {"unit": "CELSIUS", "degrees": 8.5}, "feelsLikeTemperature": {"unit": "CELSIUS", "degrees": 7}, "dewPoint": {"unit": "CELSIUS", "degrees": 7}, "heatIndex": {"unit": "CELSIUS", "degrees": 8.5}, "windChill": {"unit": "CELSIUS", "degrees": 7}, "wetBulbTemperature": {"unit": "CELSIUS", "degrees": 7.8}, "precipitation": {"probability": {"type": "RAIN", "percent": 0}, "snowQpf": {"unit": "MILLIMETERS", "quantity": 0}, "qpf": {"unit": "MILLIMETERS", "quantity": 0}}, "airPressure": {"meanSeaLevelMillibars": 1027.34}, "wind": {"direction": {"cardinal": "NORTH_NORTHEAST", "degrees": 21}, "speed": {"unit": "KILOMETERS_PER_HOUR", "value": 10}, "gust": {"unit": "KILOMETERS_PER_HOUR", "value": 14}}, "visibility": {"unit": "KILOMETERS", "distance": 16}, "iceThickness": {"unit": "MILLIMETERS", "thickness": 0}, "isDaytime": false, "relativeHumidity": 90, "uvIndex": 0, "thunderstormProbability": 0, "cloudCover": 0}, {"interval": {"startTime": "2026-04-06T06:00:00Z", "endTime": "2026-04-06T07:00:00Z"}, "displayDateTime": {"year": 2026, "month": 4, "day": 6, "hours": 8, "minutes": 0, "seconds": 0, "nanos": 0, "utcOffset": "7200s"}, "weatherCondition": {"iconBaseUri": "https://maps.gstatic.com/weather/v1/sunny", "description": {"text": "Sunny", "languageCode": "en"}, "type": "CLEAR"}, "temperature": {"unit": "CELSIUS", "degrees": 9.2}, "feelsLikeTemperature": {"unit": "CELSIUS", "degrees": 8}, "dewPoint": {"unit": "CELSIUS", "degrees": 7.4}, "heatIndex": {"unit": "CELSIUS", "degrees": 9.2}, "windChill": {"unit": "CELSIUS", "degrees": 8}, "wetBulbTemperature": {"unit": "CELSIUS", "degrees": 8.2}, "precipitation": {"probability": {"type": "RAIN", "percent": 0}, "snowQpf": {"unit": "MILLIMETERS", "quantity": 0}, "qpf": {"unit": "MILLIMETERS", "quantity": 0}}, "airPressure": {"meanSeaLevelMillibars": 1027.3}, "wind": {"direction": {"cardinal": "NORTH_NORTHEAST", "degrees": 18}, "speed": {"unit": "KILOMETERS_PER_HOUR", "value": 10}, "gust": {"unit": "KILOMETERS_PER_HOUR", "value": 13}}, "visibility": {"unit": "KILOMETERS", "distance": 16}, "iceThickness": {"unit": "MILLIMETERS", "thickness": 0}, "isDaytime": true, "relativeHumidity": 88, "uvIndex": 0, "thunderstormProbability": 0, "cloudCover": 1}, {"interval": {"startTime": "2026-04-06T07:00:00Z", "endTime": "2026-04-06T08:00:00Z"}, "displayDateTime": {"year": 2026, "month": 4, "day": 6, "hours": 9, "minutes": 0, "seconds": 0, "nanos": 0, "utcOffset": "7200s"}, "weatherCondition": {"iconBaseUri": "https://maps.gstatic.com/weather/v1/sunny", "description": {"text": "Sunny", "languageCode": "en"}, "type": "CLEAR"}, "temperature": {"unit": "CELSIUS", "degrees": 10.5}, "feelsLikeTemperature": {"unit": "CELSIUS", "degrees": 9}, "dewPoint": {"unit": "CELSIUS", "degrees": 8.2}, "heatIndex": {"unit": "CELSIUS", "degrees": 10.5}, "windChill": {"unit": "CELSIUS", "degrees": 9}, "wetBulbTemperature": {"unit": "CELSIUS", "degrees": 9.2}, "precipitation": {"probability": {"type": "RAIN", "percent": 0}, "snowQpf": {"unit": "MILLIMETERS", "quantity": 0}, "qpf": {"unit": "MILLIMETERS", "quantity": 0}}, "airPressure": {"meanSeaLevelMillibars": 1027.56}, "wind": {"direction": {"cardinal": "NORTH_NORTHEAST", "degrees": 21}, "speed": {"unit": "KILOMETERS_PER_HOUR", "value": 10}, "gust": {"unit": "KILOMETERS_PER_HOUR", "value": 16}}, "visibility": {"unit": "KILOMETERS", "distance": 16}, "iceThickness": {"unit": "MILLIMETERS", "thickness": 0}, "isDaytime": true, "relativeHumidity": 85, "uvIndex": 0, "thunderstormProbability": 0, "cloudCover": 0}, {"interval": {"startTime": "2026-04-06T08:00:00Z", "endTime": "2026-04-06T09:00:00Z"}, "displayDateTime": {"year": 2026, "month": 4, "day": 6, "hours": 10, "minutes": 0, "seconds": 0, "nanos": 0, "utcOffset": "7200s"}, "weatherCondition": {"iconBaseUri": "https://maps.gstatic.com/weather/v1/sunny", "description": {"text": "Sunny", "languageCode": "en"}, "type": "CLEAR"}, "temperature": {"unit": "CELSIUS", "degrees": 12}, "feelsLikeTemperature": {"unit": "CELSIUS", "degrees": 11}, "dewPoint": {"unit": "CELSIUS", "degrees": 9}, "heatIndex": {"unit": "CELSIUS", "degrees": 12}, "windChill": {"unit": "CELSIUS", "degrees": 11}, "wetBulbTemperature": {"unit": "CELSIUS", "degrees": 10.3}, "precipitation": {"probability": {"type": "RAIN", "percent": 0}, "snowQpf": {"unit": "MILLIMETERS", "quantity": 0}, "qpf": {"unit": "MILLIMETERS", "quantity": 0}}, "airPressure": {"meanSeaLevelMillibars": 1027.63}, "wind": {"direction": {"cardinal": "NORTH_NORTHEAST", "degrees": 27}, "speed": {"unit": "KILOMETERS_PER_HOUR", "value": 10}, "gust": {"unit": "KILOMETERS_PER_HOUR", "value": 18}}, "visibility": {"unit": "KILOMETERS", "distance": 16}, "iceThickness": {"unit": "MILLIMETERS", "thickness": 0}, "isDaytime": true, "relativeHumidity": 81, "uvIndex": 1, "thunderstormProbability": 0, "cloudCover": 2}, {"interval": {"startTime": "2026-04-06T09:00:00Z", "endTime": "2026-04-06T10:00:00Z"}, "displayDateTime": {"year": 2026, "month": 4, "day": 6, "hours": 11, "minutes": 0, "seconds": 0, "nanos": 0, "utcOffset": "7200s"}, "weatherCondition": {"iconBaseUri": "https://maps.gstatic.com/weather/v1/sunny", "description": {"text": "Sunny", "languageCode": "en"}, "type": "CLEAR"}, "temperature": {"unit": "CELSIUS", "degrees": 13.6}, "feelsLikeTemperature": {"unit": "CELSIUS", "degrees": 13}, "dewPoint": {"unit": "CELSIUS", "degrees": 9.8}, "heatIndex": {"unit": "CELSIUS", "degrees": 13.6}, "windChill": {"unit": "CELSIUS", "degrees": 13}, "wetBulbTemperature": {"unit": "CELSIUS", "degrees": 11.4}, "precipitation": {"probability": {"type": "RAIN", "percent": 0}, "snowQpf": {"unit": "MILLIMETERS", "quantity": 0}, "qpf": {"unit": "MILLIMETERS", "quantity": 0}}, "airPressure": {"meanSeaLevelMillibars": 1027.46}, "wind": {"direction": {"cardinal": "NORTH_NORTHEAST", "degrees": 26}, "speed": {"unit": "KILOMETERS_PER_HOUR", "value": 8}, "gust": {"unit": "KILOMETERS_PER_HOUR", "value": 18}}, "visibility": {"unit": "KILOMETERS", "distance": 16}, "iceThickness": {"unit": "MILLIMETERS", "thickness": 0}, "isDaytime": true, "relativeHumidity": 77, "uvIndex": 3, "thunderstormProbability": 0, "cloudCover": 1}, {"interval": {"startTime": "2026-04-06T10:00:00Z", "endTime": "2026-04-06T11:00:00Z"}, "displayDateTime": {"year": 2026, "month": 4, "day": 6, "hours": 12, "minutes": 0, "seconds": 0, "nanos": 0, "utcOffset": "7200s"}, "weatherCondition": {"iconBaseUri": "https://maps.gstatic.com/weather/v1/sunny", "description": {"text": "Sunny", "languageCode": "en"}, "type": "CLEAR"}, "temperature": {"unit": "CELSIUS", "degrees": 15.2}, "feelsLikeTemperature": {"unit": "CELSIUS", "degrees": 15}, "dewPoint": {"unit": "CELSIUS", "degrees": 10.3}, "heatIndex": {"unit": "CELSIUS", "degrees": 15.2}, "windChill": {"unit": "CELSIUS", "degrees": 15}, "wetBulbTemperature": {"unit": "CELSIUS", "degrees": 12.3}, "precipitation": {"probability": {"type": "RAIN", "percent": 0}, "snowQpf": {"unit": "MILLIMETERS", "quantity": 0}, "qpf": {"unit": "MILLIMETERS", "quantity": 0}}, "airPressure": {"meanSeaLevelMillibars": 1027.13}, "wind": {"direction": {"cardinal": "NORTH_NORTHEAST", "degrees": 24}, "speed": {"unit": "KILOMETERS_PER_HOUR", "value": 8}, "gust": {"unit": "KILOMETERS_PER_HOUR", "value": 14}}, "visibility": {"unit": "KILOMETERS", "distance": 16}, "iceThickness": {"unit": "MILLIMETERS", "thickness": 0}, "isDaytime": true, "relativeHumidity": 72, "uvIndex": 4, "thunderstormProbability": 0, "cloudCover": 0}, {"interval": {"startTime": "2026-04-06T11:00:00Z", "endTime": "2026-04-06T12:00:00Z"}, "displayDateTime": {"year": 2026, "month": 4, "day": 6, "hours": 13, "minutes": 0, "seconds": 0, "nanos": 0, "utcOffset": "7200s"}, "weatherCondition": {"iconBaseUri": "https://maps.gstatic.com/weather/v1/sunny", "description": {"text": "Sunny", "languageCode": "en"}, "type": "CLEAR"}, "temperature": {"unit": "CELSIUS", "degrees": 16.5}, "feelsLikeTemperature": {"unit": "CELSIUS", "degrees": 16.5}, "dewPoint": {"unit": "CELSIUS", "degrees": 10.6}, "heatIndex": {"unit": "CELSIUS", "degrees": 16.5}, "windChill": {"unit": "CELSIUS", "degrees": 16.5}, "wetBulbTemperature": {"unit": "CELSIUS", "degrees": 13}, "precipitation": {"probability": {"type": "RAIN", "percent": 0}, "snowQpf": {"unit": "MILLIMETERS", "quantity": 0}, "qpf": {"unit": "MILLIMETERS", "quantity": 0}}, "airPressure": {"meanSeaLevelMillibars": 1026.61}, "wind": {"direction": {"cardinal": "NORTHEAST", "degrees": 35}, "speed": {"unit": "KILOMETERS_PER_HOUR", "value": 8}, "gust": {"unit": "KILOMETERS_PER_HOUR", "value": 14}}, "visibility": {"unit": "KILOMETERS", "distance": 16}, "iceThickness": {"unit": "MILLIMETERS", "thickness": 0}, "isDaytime": true, "relativeHumidity": 68, "uvIndex": 5, "thunderstormProbability": 0, "cloudCover": 0}, {"interval": {"startTime": "2026-04-06T12:00:00Z", "endTime": "2026-04-06T13:00:00Z"}, "displayDateTime": {"year": 2026, "month": 4, "day": 6, "hours": 14, "minutes": 0, "seconds": 0, "nanos": 0, "utcOffset": "7200s"}, "weatherCondition": {"iconBaseUri": "https://maps.gstatic.com/weather/v1/sunny", "description": {"text": "Sunny", "languageCode": "en"}, "type": "CLEAR"}, "temperature": {"unit": "CELSIUS", "degrees": 17.7}, "feelsLikeTemperature": {"unit": "CELSIUS", "degrees": 17.7}, "dewPoint": {"unit": "CELSIUS", "degrees": 10.8}, "heatIndex": {"unit": "CELSIUS", "degrees": 17.7}, "windChill": {"unit": "CELSIUS", "degrees": 17.7}, "wetBulbTemperature": {"unit": "CELSIUS", "degrees": 13.6}, "precipitation": {"probability": {"type": "RAIN", "percent": 0}, "snowQpf": {"unit": "MILLIMETERS", "quantity": 0}, "qpf": {"unit": "MILLIMETERS", "quantity": 0}}, "airPressure": {"meanSeaLevelMillibars": 1025.49}, "wind": {"direction": {"cardinal": "NORTHEAST", "degrees": 40}, "speed": {"unit": "KILOMETERS_PER_HOUR", "value": 8}, "gust": {"unit": "KILOMETERS_PER_HOUR", "value": 18}}, "visibility": {"unit": "KILOMETERS", "distance": 16}, "iceThickness": {"unit": "MILLIMETERS", "thickness": 0}, "isDaytime": true, "relativeHumidity": 64, "uvIndex": 5, "thunderstormProbability": 0, "cloudCover": 1}, {"interval": {"startTime": "2026-04-06T13:00:00Z", "endTime": "2026-04-06T14:00:00Z"}, "displayDateTime": {"year": 2026, "month": 4, "day": 6, "hours": 15, "minutes": 0, "seconds": 0, "nanos": 0, "utcOffset": "7200s"}, "weatherCondition": {"iconBaseUri": "https://maps.gstatic.com/weather/v1/sunny", "description": {"text": "Sunny", "languageCode": "en"}, "type": "CLEAR"}, "temperature": {"unit": "CELSIUS", "degrees": 18.7}, "feelsLikeTemperature": {"unit": "CELSIUS", "degrees": 18.7}, "dewPoint": {"unit": "CELSIUS", "degrees": 11.1}, "heatIndex": {"unit": "CELSIUS", "degrees": 18.7}, "windChill": {"unit": "CELSIUS", "degrees": 18.7}, "wetBulbTemperature": {"unit": "CELSIUS", "degrees": 14.1}, "precipitation": {"probability": {"type": "RAIN", "percent": 0}, "snowQpf": {"unit": "MILLIMETERS", "quantity": 0}, "qpf": {"unit": "MILLIMETERS", "quantity": 0}}, "airPressure": {"meanSeaLevelMillibars": 1024.71}, "wind": {"direction": {"cardinal": "NORTHEAST", "degrees": 42}, "speed": {"unit": "KILOMETERS_PER_HOUR", "value": 6}, "gust": {"unit": "KILOMETERS_PER_HOUR", "value": 14}}, "visibility": {"unit": "KILOMETERS", "distance": 16}, "iceThickness": {"unit": "MILLIMETERS", "thickness": 0}, "isDaytime": true, "relativeHumidity": 61, "uvIndex": 4, "thunderstormProbability": 0, "cloudCover": 11}, {"interval": {"startTime": "2026-04-06T14:00:00Z", "endTime": "2026-04-06T15:00:00Z"}, "displayDateTime": {"year": 2026, "month": 4, "day": 6, "hours": 16, "minutes": 0, "seconds": 0, "nanos": 0, "utcOffset": "7200s"}, "weatherCondition": {"iconBaseUri": "https://maps.gstatic.com/weather/v1/sunny", "description": {"text": "Sunny", "languageCode": "en"}, "type": "CLEAR"}, "temperature": {"unit": "CELSIUS", "degrees": 19.5}, "feelsLikeTemperature": {"unit": "CELSIUS", "degrees": 24.6}, "dewPoint": {"unit": "CELSIUS", "degrees": 11.2}, "heatIndex": {"unit": "CELSIUS", "degrees": 24.6}, "windChill": {"unit": "CELSIUS", "degrees": 19.5}, "wetBulbTemperature": {"unit": "CELSIUS", "degrees": 14.5}, "precipitation": {"probability": {"type": "RAIN", "percent": 0}, "snowQpf": {"unit": "MILLIMETERS", "quantity": 0}, "qpf": {"unit": "MILLIMETERS", "quantity": 0}}, "airPressure": {"meanSeaLevelMillibars": 1024.1}, "wind": {"direction": {"cardinal": "NORTHEAST", "degrees": 44}, "speed": {"unit": "KILOMETERS_PER_HOUR", "value": 6}, "gust": {"unit": "KILOMETERS_PER_HOUR", "value": 13}}, "visibility": {"unit": "KILOMETERS", "distance": 16}, "iceThickness": {"unit": "MILLIMETERS", "thickness": 0}, "isDaytime": true, "relativeHumidity": 58, "uvIndex": 3, "thunderstormProbability": 0, "cloudCover": 12}, {"interval": {"startTime": "2026-04-06T15:00:00Z", "endTime": "2026-04-06T16:00:00Z"}, "displayDateTime": {"year": 2026, "month": 4, "day": 6, "hours": 17, "minutes": 0, "seconds": 0, "nanos": 0, "utcOffset": "7200s"}, "weatherCondition": {"iconBaseUri": "https://maps.gstatic.com/weather/v1/sunny", "description": {"text": "Sunny", "languageCode": "en"}, "type": "CLEAR"}, "temperature": {"unit": "CELSIUS", "degrees": 20.1}, "feelsLikeTemperature": {"unit": "CELSIUS", "degrees": 24.5}, "dewPoint": {"unit": "CELSIUS", "degrees": 11.3}, "heatIndex": {"unit": "CELSIUS", "degrees": 24.5}, "windChill": {"unit": "CELSIUS", "degrees": 20.1}, "wetBulbTemperature": {"unit": "CELSIUS", "degrees": 14.7}, "precipitation": {"probability": {"type": "RAIN", "percent": 0}, "snowQpf": {"unit": "MILLIMETERS", "quantity": 0}, "qpf": {"unit": "MILLIMETERS", "quantity": 0}}, "airPressure": {"meanSeaLevelMillibars": 1023.55}, "wind": {"direction": {"cardinal": "NORTHEAST", "degrees": 46}, "speed": {"unit": "KILOMETERS_PER_HOUR", "value": 8}, "gust": {"unit": "KILOMETERS_PER_HOUR", "value": 13}}, "visibility": {"unit": "KILOMETERS", "distance": 16}, "iceThickness": {"unit": "MILLIMETERS", "thickness": 0}, "isDaytime": true, "relativeHumidity": 56, "uvIndex": 2, "thunderstormProbability": 0, "cloudCover": 13}, {"interval": {"startTime": "2026-04-06T16:00:00Z", "endTime": "2026-04-06T17:00:00Z"}, "displayDateTime": {"year": 2026, "month": 4, "day": 6, "hours": 18, "minutes": 0, "seconds": 0, "nanos": 0, "utcOffset": "7200s"}, "weatherCondition": {"iconBaseUri": "https://maps.gstatic.com/weather/v1/sunny", "description": {"text": "Sunny", "languageCode": "en"}, "type": "CLEAR"}, "temperature": {"unit": "CELSIUS", "degrees": 19.6}, "feelsLikeTemperature": {"unit": "CELSIUS", "degrees": 24.6}, "dewPoint": {"unit": "CELSIUS", "degrees": 11}, "heatIndex": {"unit": "CELSIUS", "degrees": 24.6}, "windChill": {"unit": "CELSIUS", "degrees": 19.6}, "wetBulbTemperature": {"unit": "CELSIUS", "degrees": 14.4}, "precipitation": {"probability": {"type": "RAIN", "percent": 0}, "snowQpf": {"unit": "MILLIMETERS", "quantity": 0}, "qpf": {"unit": "MILLIMETERS", "quantity": 0}}, "airPressure": {"meanSeaLevelMillibars": 1023.14}, "wind": {"direction": {"cardinal": "NORTHEAST", "degrees": 47}, "speed": {"unit": "KILOMETERS_PER_HOUR", "value": 8}, "gust": {"unit": "KILOMETERS_PER_HOUR", "value": 13}}, "visibility": {"unit": "KILOMETERS", "distance": 16}, "iceThickness": {"unit": "MILLIMETERS", "thickness": 0}, "isDaytime": true, "relativeHumidity": 57, "uvIndex": 1, "thunderstormProbability": 0, "cloudCover": 15}, {"interval": {"startTime": "2026-04-06T17:00:00Z", "endTime": "2026-04-06T18:00:00Z"}, "displayDateTime": {"year": 2026, "month": 4, "day": 6, "hours": 19, "minutes": 0, "seconds": 0, "nanos": 0, "utcOffset": "7200s"}, "weatherCondition": {"iconBaseUri": "https://maps.gstatic.com/weather/v1/sunny", "description": {"text": "Sunny", "languageCode": "en"}, "type": "CLEAR"}, "temperature": {"unit": "CELSIUS", "degrees": 18.7}, "feelsLikeTemperature": {"unit": "CELSIUS", "degrees": 18.7}, "dewPoint": {"unit": "CELSIUS", "degrees": 11.1}, "heatIndex": {"unit": "CELSIUS", "degrees": 18.7}, "windChill": {"unit": "CELSIUS", "degrees": 18.7}, "wetBulbTemperature": {"unit": "CELSIUS", "degrees": 14.1}, "precipitation": {"probability": {"type": "RAIN", "percent": 0}, "snowQpf": {"unit": "MILLIMETERS", "quantity": 0}, "qpf": {"unit": "MILLIMETERS", "quantity": 0}}, "airPressure": {"meanSeaLevelMillibars": 1022.85}, "wind": {"direction": {"cardinal": "NORTHEAST", "degrees": 41}, "speed": {"unit": "KILOMETERS_PER_HOUR", "value": 8}, "gust": {"unit": "KILOMETERS_PER_HOUR", "value": 14}}, "visibility": {"unit": "KILOMETERS", "distance": 16}, "iceThickness": {"unit": "MILLIMETERS", "thickness": 0}, "isDaytime": true, "relativeHumidity": 61, "uvIndex": 0, "thunderstormProbability": 0, "cloudCover": 19}, {"interval": {"startTime": "2026-04-06T18:00:00Z", "endTime": "2026-04-06T19:00:00Z"}, "displayDateTime": {"year": 2026, "month": 4, "day": 6, "hours": 20, "minutes": 0, "seconds": 0, "nanos": 0, "utcOffset": "7200s"}, "weatherCondition": {"iconBaseUri": "https://maps.gstatic.com/weather/v1/sunny", "description": {"text": "Sunny", "languageCode": "en"}, "type": "CLEAR"}, "temperature": {"unit": "CELSIUS", "degrees": 16.2}, "feelsLikeTemperature": {"unit": "CELSIUS", "degrees": 16}, "dewPoint": {"unit": "CELSIUS", "degrees": 10.4}, "heatIndex": {"unit": "CELSIUS", "degrees": 16.2}, "windChill": {"unit": "CELSIUS", "degrees": 16}, "wetBulbTemperature": {"unit": "CELSIUS", "degrees": 12.8}, "precipitation": {"probability": {"type": "RAIN", "percent": 0}, "snowQpf": {"unit": "MILLIMETERS", "quantity": 0}, "qpf": {"unit": "MILLIMETERS", "quantity": 0}}, "airPressure": {"meanSeaLevelMillibars": 1022.65}, "wind": {"direction": {"cardinal": "NORTH_NORTHEAST", "degrees": 32}, "speed": {"unit": "KILOMETERS_PER_HOUR", "value": 8}, "gust": {"unit": "KILOMETERS_PER_HOUR", "value": 11}}, "visibility": {"unit": "KILOMETERS", "distance": 16}, "iceThickness": {"unit": "MILLIMETERS", "thickness": 0}, "isDaytime": true, "relativeHumidity": 68, "uvIndex": 0, "thunderstormProbability": 0, "cloudCover": 19}, {"interval": {"startTime": "2026-04-06T19:00:00Z", "endTime": "2026-04-06T20:00:00Z"}, "displayDateTime": {"year": 2026, "month": 4, "day": 6, "hours": 21, "minutes": 0, "seconds": 0, "nanos": 0, "utcOffset": "7200s"}, "weatherCondition": {"iconBaseUri": "https://maps.gstatic.com/weather/v1/clear", "description": {"text": "Clear", "languageCode": "en"}, "type": "CLEAR"}, "temperature": {"unit": "CELSIUS", "degrees": 14.1}, "feelsLikeTemperature": {"unit": "CELSIUS", "degrees": 14}, "dewPoint": {"unit": "CELSIUS", "degrees": 9.8}, "heatIndex": {"unit": "CELSIUS", "degrees": 14.1}, "windChill": {"unit": "CELSIUS", "degrees": 14}, "wetBulbTemperature": {"unit": "CELSIUS", "degrees": 11.6}, "precipitation": {"probability": {"type": "RAIN", "percent": 0}, "snowQpf": {"unit": "MILLIMETERS", "quantity": 0}, "qpf": {"unit": "MILLIMETERS", "quantity": 0}}, "airPressure": {"meanSeaLevelMillibars": 1022.69}, "wind": {"direction": {"cardinal": "NORTH_NORTHEAST", "degrees": 33}, "speed": {"unit": "KILOMETERS_PER_HOUR", "value": 8}, "gust": {"unit": "KILOMETERS_PER_HOUR", "value": 11}}, "visibility": {"unit": "KILOMETERS", "distance": 16}, "iceThickness": {"unit": "MILLIMETERS", "thickness": 0}, "isDaytime": false, "relativeHumidity": 75, "uvIndex": 0, "thunderstormProbability": 0, "cloudCover": 6}, {"interval": {"startTime": "2026-04-06T20:00:00Z", "endTime": "2026-04-06T21:00:00Z"}, "displayDateTime": {"year": 2026, "month": 4, "day": 6, "hours": 22, "minutes": 0, "seconds": 0, "nanos": 0, "utcOffset": "7200s"}, "weatherCondition": {"iconBaseUri": "https://maps.gstatic.com/weather/v1/clear", "description": {"text": "Clear", "languageCode": "en"}, "type": "CLEAR"}, "temperature": {"unit": "CELSIUS", "degrees": 12.6}, "feelsLikeTemperature": {"unit": "CELSIUS", "degrees": 12}, "dewPoint": {"unit": "CELSIUS", "degrees": 9.2}, "heatIndex": {"unit": "CELSIUS", "degrees": 12.6}, "windChill": {"unit": "CELSIUS", "degrees": 12}, "wetBulbTemperature": {"unit": "CELSIUS", "degrees": 10.7}, "precipitation": {"probability": {"type": "RAIN", "percent": 0}, "snowQpf": {"unit": "MILLIMETERS", "quantity": 0}, "qpf": {"unit": "MILLIMETERS", "quantity": 0}}, "airPressure": {"meanSeaLevelMillibars": 1022.97}, "wind": {"direction": {"cardinal": "NORTH_NORTHEAST", "degrees": 28}, "speed": {"unit": "KILOMETERS_PER_HOUR", "value": 8}, "gust": {"unit": "KILOMETERS_PER_HOUR", "value": 11}}, "visibility": {"unit": "KILOMETERS", "distance": 16}, "iceThickness": {"unit": "MILLIMETERS", "thickness": 0}, "isDaytime": false, "relativeHumidity": 79, "uvIndex": 0, "thunderstormProbability": 0, "cloudCover": 1}], "timeZone": {"id": "Europe/Paris", "version": ""}, "nextPageToken": "ChcKEglNol7waW5HQBFffTz03V0UQBDwARAwGDAiDAivjsbOBhCg64eYASoMRXVyb3BlL1Bhcmlz"}