{"forecastHours": [{"interval": {"startTime": "2026-04-12T06:00:00Z", "endTime": "2026-04-12T07:00:00Z"}, "displayDateTime": {"year": 2026, "month": 4, "day": 12, "hours": 9, "minutes": 0, "seconds": 0, "nanos": 0, "utcOffset": "10800s"}, "weatherCondition": {"iconBaseUri": "https://maps.gstatic.com/weather/v1/wintry_mix", "description": {"text": "Rain and snow", "languageCode": "en"}, "type": "RAIN_AND_SNOW"}, "temperature": {"unit": "CELSIUS", "degrees": 0.4}, "feelsLikeTemperature": {"unit": "CELSIUS", "degrees": -2}, "dewPoint": {"unit": "CELSIUS", "degrees": -2.6}, "heatIndex": {"unit": "CELSIUS", "degrees": 0.4}, "windChill": {"unit": "CELSIUS", "degrees": -2}, "wetBulbTemperature": {"unit": "CELSIUS", "degrees": -0.8}, "precipitation": {"probability": {"type": "RAIN_AND_SNOW", "percent": 35}, "snowQpf": {"unit": "MILLIMETERS", "quantity": 1.12}, "qpf": {"unit": "MILLIMETERS", "quantity": 0.27}}, "airPressure": {"meanSeaLevelMillibars": 1012.92}, "wind": {"direction": {"cardinal": "NORTHEAST", "degrees": 51}, "speed": {"unit": "KILOMETERS_PER_HOUR", "value": 6}, "gust": {"unit": "KILOMETERS_PER_HOUR", "value": 16}}, "visibility": {"unit": "KILOMETERS", "distance": 16}, "iceThickness": {"unit": "MILLIMETERS", "thickness": 0}, "isDaytime": true, "relativeHumidity": 80, "uvIndex": 0, "thunderstormProbability": 10, "cloudCover": 70}, {"interval": {"startTime": "2026-04-12T07:00:00Z", "endTime": "2026-04-12T08:00:00Z"}, "displayDateTime": {"year": 2026, "month": 4, "day": 12, "hours": 10, "minutes": 0, "seconds": 0, "nanos": 0, "utcOffset": "10800s"}, "weatherCondition": {"iconBaseUri": "https://maps.gstatic.com/weather/v1/mostly_cloudy", "description": {"text": "Mostly cloudy", "languageCode": "en"}, "type": "MOSTLY_CLOUDY"}, "temperature": {"unit": "CELSIUS", "degrees": 1.9}, "feelsLikeTemperature": {"unit": "CELSIUS", "degrees": 0}, "dewPoint": {"unit": "CELSIUS", "degrees": -2.3}, "heatIndex": {"unit": "CELSIUS", "degrees": 1.9}, "windChill": {"unit": "CELSIUS", "degrees": 0}, "wetBulbTemperature": {"unit": "CELSIUS", "degrees": 0}, "precipitation": {"probability": {"type": "RAIN", "percent": 10}, "snowQpf": {"unit": "MILLIMETERS", "quantity": 0}, "qpf": {"unit": "MILLIMETERS", "quantity": 0}}, "airPressure": {"meanSeaLevelMillibars": 1013.2}, "wind": {"direction": {"cardinal": "EAST_NORTHEAST", "degrees": 73}, "speed": {"unit": "KILOMETERS_PER_HOUR", "value": 6}, "gust": {"unit": "KILOMETERS_PER_HOUR", "value": 19}}, "visibility": {"unit": "KILOMETERS", "distance": 16}, "iceThickness": {"unit": "MILLIMETERS", "thickness": 0}, "isDaytime": true, "relativeHumidity": 73, "uvIndex": 2, "thunderstormProbability": 0, "cloudCover": 66}, {"interval": {"startTime": "2026-04-12T08:00:00Z", "endTime": "2026-04-12T09:00:00Z"}, "displayDateTime": {"year": 2026, "month": 4, "day": 12, "hours": 11, "minutes": 0, "seconds": 0, "nanos": 0, "utcOffset": "10800s"}, "weatherCondition": {"iconBaseUri": "https://maps.gstatic.com/weather/v1/partly_cloudy", "description": {"text": "Partly sunny", "languageCode": "en"}, "type": "PARTLY_CLOUDY"}, "temperature": {"unit": "CELSIUS", "degrees": 3.3}, "feelsLikeTemperature": {"unit": "CELSIUS", "degrees": 1}, "dewPoint": {"unit": "CELSIUS", "degrees": -2.1}, "heatIndex": {"unit": "CELSIUS", "degrees": 3.3}, "windChill": {"unit": "CELSIUS", "degrees": 1}, "wetBulbTemperature": {"unit": "CELSIUS", "degrees": 1}, "precipitation": {"probability": {"type": "RAIN", "percent": 5}, "snowQpf": {"unit": "MILLIMETERS", "quantity": 0}, "qpf": {"unit": "MILLIMETERS", "quantity": 0}}, "airPressure": {"meanSeaLevelMillibars": 1013.32}, "wind": {"direction": {"cardinal": "EAST_NORTHEAST", "degrees": 78}, "speed": {"unit": "KILOMETERS_PER_HOUR", "value": 8}, "gust": {"unit": "KILOMETERS_PER_HOUR", "value": 23}}, "visibility": {"unit": "KILOMETERS", "distance": 16}, "iceThickness": {"unit": "MILLIMETERS", "thickness": 0}, "isDaytime": true, "relativeHumidity": 67, "uvIndex": 3, "thunderstormProbability": 0, "cloudCover": 62}, {"interval": {"startTime": "2026-04-12T09:00:00Z", "endTime": "2026-04-12T10:00:00Z"}, "displayDateTime": {"year": 2026, "month": 4, "day": 12, "hours": 12, "minutes": 0, "seconds": 0, "nanos": 0, "utcOffset": "10800s"}, "weatherCondition": {"iconBaseUri": "https://maps.gstatic.com/weather/v1/partly_cloudy", "description": {"text": "Partly sunny", "languageCode": "en"}, "type": "PARTLY_CLOUDY"}, "temperature": {"unit": "CELSIUS", "degrees": 4.8}, "feelsLikeTemperature": {"unit": "CELSIUS", "degrees": 3}, "dewPoint": {"unit": "CELSIUS", "degrees": -1.9}, "heatIndex": {"unit": "CELSIUS", "degrees": 4.8}, "windChill": {"unit": "CELSIUS", "degrees": 3}, "wetBulbTemperature": {"unit": "CELSIUS", "degrees": 1.8}, "precipitation": {"probability": {"type": "RAIN", "percent": 5}, "snowQpf": {"unit": "MILLIMETERS", "quantity": 0}, "qpf": {"unit": "MILLIMETERS", "quantity": 0}}, "airPressure": {"meanSeaLevelMillibars": 1013.18}, "wind": {"direction": {"cardinal": "EAST", "degrees": 83}, "speed": {"unit": "KILOMETERS_PER_HOUR", "value": 8}, "gust": {"unit": "KILOMETERS_PER_HOUR", "value": 24}}, "visibility": {"unit": "KILOMETERS", "distance": 16}, "iceThickness": {"unit": "MILLIMETERS", "thickness": 0}, "isDaytime": true, "relativeHumidity": 61, "uvIndex": 5, "thunderstormProbability": 0, "cloudCover": 58}, {"interval": {"startTime": "2026-04-12T10:00:00Z", "endTime": "2026-04-12T11:00:00Z"}, "displayDateTime": {"year": 2026, "month": 4, "day": 12, "hours": 13, "minutes": 0, "seconds": 0, "nanos": 0, "utcOffset": "10800s"}, "weatherCondition": {"iconBaseUri": "https://maps.gstatic.com/weather/v1/partly_cloudy", "description": {"text": "Partly sunny", "languageCode": "en"}, "type": "PARTLY_CLOUDY"}, "temperature": {"unit": "CELSIUS", "degrees": 5.9}, "feelsLikeTemperature": {"unit": "CELSIUS", "degrees": 4}, "dewPoint": {"unit": "CELSIUS", "degrees": -1.9}, "heatIndex": {"unit": "CELSIUS", "degrees": 5.9}, "windChill": {"unit": "CELSIUS", "degrees": 4}, "wetBulbTemperature": {"unit": "CELSIUS", "degrees": 2.4}, "precipitation": {"probability": {"type": "RAIN", "percent": 5}, "snowQpf": {"unit": "MILLIMETERS", "quantity": 0}, "qpf": {"unit": "MILLIMETERS", "quantity": 0}}, "airPressure": {"meanSeaLevelMillibars": 1012.77}, "wind": {"direction": {"cardinal": "EAST", "degrees": 85}, "speed": {"unit": "KILOMETERS_PER_HOUR", "value": 8}, "gust": {"unit": "KILOMETERS_PER_HOUR", "value": 24}}, "visibility": {"unit": "KILOMETERS", "distance": 16}, "iceThickness": {"unit": "MILLIMETERS", "thickness": 0}, "isDaytime": true, "relativeHumidity": 57, "uvIndex": 6, "thunderstormProbability": 0, "cloudCover": 58}, {"interval": {"startTime": "2026-04-12T11:00:00Z", "endTime": "2026-04-12T12:00:00Z"}, "displayDateTime": {"year": 2026, "month": 4, "day": 12, "hours": 14, "minutes": 0, "seconds": 0, "nanos": 0, "utcOffset": "10800s"}, "weatherCondition": {"iconBaseUri": "https://maps.gstatic.com/weather/v1/partly_cloudy", "description": {"text": "Partly sunny", "languageCode": "en"}, "type": "PARTLY_CLOUDY"}, "temperature": {"unit": "CELSIUS", "degrees": 6.8}, "feelsLikeTemperature": {"unit": "CELSIUS", "degrees": 5}, "dewPoint": {"unit": "CELSIUS", "degrees": -1.8}, "heatIndex": {"unit": "CELSIUS", "degrees": 6.8}, "windChill": {"unit": "CELSIUS", "degrees": 5}, "wetBulbTemperature": {"unit": "CELSIUS", "degrees": 2.9}, "precipitation": {"probability": {"type": "RAIN", "percent": 5}, "snowQpf": {"unit": "MILLIMETERS", "quantity": 0}, "qpf": {"unit": "MILLIMETERS", "quantity": 0}}, "airPressure": {"meanSeaLevelMillibars": 1012.22}, "wind": {"direction": {"cardinal": "EAST", "degrees": 85}, "speed": {"unit": "KILOMETERS_PER_HOUR", "value": 10}, "gust": {"unit": "KILOMETERS_PER_HOUR", "value": 26}}, "visibility": {"unit": "KILOMETERS", "distance": 16}, "iceThickness": {"unit": "MILLIMETERS", "thickness": 0}, "isDaytime": true, "relativeHumidity": 54, "uvIndex": 6, "thunderstormProbability": 0, "cloudCover": 59}, {"interval": {"startTime": "2026-04-12T12:00:00Z", "endTime": "2026-04-12T13:00:00Z"}, "displayDateTime": {"year": 2026, "month": 4, "day": 12, "hours": 15, "minutes": 0, "seconds": 0, "nanos": 0, "utcOffset": "10800s"}, "weatherCondition": {"iconBaseUri": "https://maps.gstatic.com/weather/v1/partly_cloudy", "description": {"text": "Partly sunny", "languageCode": "en"}, "type": "PARTLY_CLOUDY"}, "temperature": {"unit": "CELSIUS", "degrees": 6.3}, "feelsLikeTemperature": {"unit": "CELSIUS", "degrees": 4}, "dewPoint": {"unit": "CELSIUS", "degrees": -1.7}, "heatIndex": {"unit": "CELSIUS", "degrees": 6.3}, "windChill": {"unit": "CELSIUS", "degrees": 4}, "wetBulbTemperature": {"unit": "CELSIUS", "degrees": 2.6}, "precipitation": {"probability": {"type": "RAIN", "percent": 5}, "snowQpf": {"unit": "MILLIMETERS", "quantity": 0}, "qpf": {"unit": "MILLIMETERS", "quantity": 0}}, "airPressure": {"meanSeaLevelMillibars": 1011.66}, "wind": {"direction": {"cardinal": "EAST_NORTHEAST", "degrees": 77}, "speed": {"unit": "KILOMETERS_PER_HOUR", "value": 10}, "gust": {"unit": "KILOMETERS_PER_HOUR", "value": 27}}, "visibility": {"unit": "KILOMETERS", "distance": 16}, "iceThickness": {"unit": "MILLIMETERS", "thickness": 0}, "isDaytime": true, "relativeHumidity": 56, "uvIndex": 5, "thunderstormProbability": 0, "cloudCover": 59}, {"interval": {"startTime": "2026-04-12T13:00:00Z", "endTime": "2026-04-12T14:00:00Z"}, "displayDateTime": {"year": 2026, "month": 4, "day": 12, "hours": 16, "minutes": 0, "seconds": 0, "nanos": 0, "utcOffset": "10800s"}, "weatherCondition": {"iconBaseUri": "https://maps.gstatic.com/weather/v1/partly_cloudy", "description": {"text": "Partly sunny", "languageCode": "en"}, "type": "PARTLY_CLOUDY"}, "temperature": {"unit": "CELSIUS", "degrees": 6.5}, "feelsLikeTemperature": {"unit": "CELSIUS", "degrees": 5}, "dewPoint": {"unit": "CELSIUS", "degrees": -1.6}, "heatIndex": {"unit": "CELSIUS", "degrees": 6.5}, "windChill": {"unit": "CELSIUS", "degrees": 5}, "wetBulbTemperature": {"unit": "CELSIUS", "degrees": 2.8}, "precipitation": {"probability": {"type": "RAIN", "percent": 5}, "snowQpf": {"unit": "MILLIMETERS", "quantity": 0}, "qpf": {"unit": "MILLIMETERS", "quantity": 0}}, "airPressure": {"meanSeaLevelMillibars": 1011.23}, "wind": {"direction": {"cardinal": "EAST", "degrees": 84}, "speed": {"unit": "KILOMETERS_PER_HOUR", "value": 10}, "gust": {"unit": "KILOMETERS_PER_HOUR", "value": 26}}, "visibility": {"unit": "KILOMETERS", "distance": 16}, "iceThickness": {"unit": "MILLIMETERS", "thickness": 0}, "isDaytime": true, "relativeHumidity": 56, "uvIndex": 3, "thunderstormProbability": 0, "cloudCover": 63}, {"interval": {"startTime": "2026-04-12T14:00:00Z", "endTime": "2026-04-12T15:00:00Z"}, "displayDateTime": {"year": 2026, "month": 4, "day": 12, "hours": 17, "minutes": 0, "seconds": 0, "nanos": 0, "utcOffset": "10800s"}, "weatherCondition": {"iconBaseUri": "https://maps.gstatic.com/weather/v1/mostly_cloudy", "description": {"text": "Mostly cloudy", "languageCode": "en"}, "type": "MOSTLY_CLOUDY"}, "temperature": {"unit": "CELSIUS", "degrees": 6.2}, "feelsLikeTemperature": {"unit": "CELSIUS", "degrees": 4}, "dewPoint": {"unit": "CELSIUS", "degrees": -1.5}, "heatIndex": {"unit": "CELSIUS", "degrees": 6.2}, "windChill": {"unit": "CELSIUS", "degrees": 4}, "wetBulbTemperature": {"unit": "CELSIUS", "degrees": 2.7}, "precipitation": {"probability": {"type": "RAIN", "percent": 10}, "snowQpf": {"unit": "MILLIMETERS", "quantity": 0}, "qpf": {"unit": "MILLIMETERS", "quantity": 0}}, "airPressure": {"meanSeaLevelMillibars": 1010.79}, "wind": {"direction": {"cardinal": "EAST", "degrees": 87}, "speed": {"unit": "KILOMETERS_PER_HOUR", "value": 8}, "gust": {"unit": "KILOMETERS_PER_HOUR", "value": 26}}, "visibility": {"unit": "KILOMETERS", "distance": 16}, "iceThickness": {"unit": "MILLIMETERS", "thickness": 0}, "isDaytime": true, "relativeHumidity": 57, "uvIndex": 2, "thunderstormProbability": 0, "cloudCover": 66}, {"interval": {"startTime": "2026-04-12T15:00:00Z", "endTime": "2026-04-12T16:00:00Z"}, "displayDateTime": {"year": 2026, "month": 4, "day": 12, "hours": 18, "minutes": 0, "seconds": 0, "nanos": 0, "utcOffset": "10800s"}, "weatherCondition": {"iconBaseUri": "https://maps.gstatic.com/weather/v1/mostly_cloudy", "description": {"text": "Mostly cloudy", "languageCode": "en"}, "type": "MOSTLY_CLOUDY"}, "temperature": {"unit": "CELSIUS", "degrees": 5.5}, "feelsLikeTemperature": {"unit": "CELSIUS", "degrees": 4}, "dewPoint": {"unit": "CELSIUS", "degrees": -1.5}, "heatIndex": {"unit": "CELSIUS", "degrees": 5.5}, "windChill": {"unit": "CELSIUS", "degrees": 4}, "wetBulbTemperature": {"unit": "CELSIUS", "degrees": 2.3}, "precipitation": {"probability": {"type": "RAIN", "percent": 10}, "snowQpf": {"unit": "MILLIMETERS", "quantity": 0}, "qpf": {"unit": "MILLIMETERS", "quantity": 0}}, "airPressure": {"meanSeaLevelMillibars": 1010.62}, "wind": {"direction": {"cardinal": "EAST", "degrees": 88}, "speed": {"unit": "KILOMETERS_PER_HOUR", "value": 8}, "gust": {"unit": "KILOMETERS_PER_HOUR", "value": 24}}, "visibility": {"unit": "KILOMETERS", "distance": 16}, "iceThickness": {"unit": "MILLIMETERS", "thickness": 0}, "isDaytime": true, "relativeHumidity": 60, "uvIndex": 0, "thunderstormProbability": 0, "cloudCover": 69}, {"interval": {"startTime": "2026-04-12T16:00:00Z", "endTime": "2026-04-12T17:00:00Z"}, "displayDateTime": {"year": 2026, "month": 4, "day": 12, "hours": 19, "minutes": 0, "seconds": 0, "nanos": 0, "utcOffset": "10800s"}, "weatherCondition": {"iconBaseUri": "https://maps.gstatic.com/weather/v1/mostly_cloudy", "description": {"text": "Mostly cloudy", "languageCode": "en"}, "type": "MOSTLY_CLOUDY"}, "temperature": {"unit": "CELSIUS", "degrees": 4.5}, "feelsLikeTemperature": {"unit": "CELSIUS", "degrees": 3}, "dewPoint": {"unit": "CELSIUS", "degrees": -1.5}, "heatIndex": {"unit": "CELSIUS", "degrees": 4.5}, "windChill": {"unit": "CELSIUS", "degrees": 3}, "wetBulbTemperature": {"unit": "CELSIUS", "degrees": 1.9}, "precipitation": {"probability": {"type": "RAIN", "percent": 10}, "snowQpf": {"unit": "MILLIMETERS", "quantity": 0}, "qpf": {"unit": "MILLIMETERS", "quantity": 0}}, "airPressure": {"meanSeaLevelMillibars": 1010.54}, "wind": {"direction": {"cardinal": "EAST", "degrees": 89}, "speed": {"unit": "KILOMETERS_PER_HOUR", "value": 8}, "gust": {"unit": "KILOMETERS_PER_HOUR", "value": 24}}, "visibility": {"unit": "KILOMETERS", "distance": 16}, "iceThickness": {"unit": "MILLIMETERS", "thickness": 0}, "isDaytime": true, "relativeHumidity": 64, "uvIndex": 0, "thunderstormProbability": 0, "cloudCover": 70}, {"interval": {"startTime": "2026-04-12T17:00:00Z", "endTime": "2026-04-12T18:00:00Z"}, "displayDateTime": {"year": 2026, "month": 4, "day": 12, "hours": 20, "minutes": 0, "seconds": 0, "nanos": 0, "utcOffset": "10800s"}, "weatherCondition": {"iconBaseUri": "https://maps.gstatic.com/weather/v1/mostly_cloudy", "description": {"text": "Mostly cloudy", "languageCode": "en"}, "type": "MOSTLY_CLOUDY"}, "temperature": {"unit": "CELSIUS", "degrees": 3.4}, "feelsLikeTemperature": {"unit": "CELSIUS", "degrees": 1}, "dewPoint": {"unit": "CELSIUS", "degrees": -1.7}, "heatIndex": {"unit": "CELSIUS", "degrees": 3.4}, "windChill": {"unit": "CELSIUS", "degrees": 1}, "wetBulbTemperature": {"unit": "CELSIUS", "degrees": 1.2}, "precipitation": {"probability": {"type": "RAIN", "percent": 10}, "snowQpf": {"unit": "MILLIMETERS", "quantity": 0}, "qpf": {"unit": "MILLIMETERS", "quantity": 0}}, "airPressure": {"meanSeaLevelMillibars": 1010.38}, "wind": {"direction": {"cardinal": "EAST", "degrees": 89}, "speed": {"unit": "KILOMETERS_PER_HOUR", "value": 8}, "gust": {"unit": "KILOMETERS_PER_HOUR", "value": 23}}, "visibility": {"unit": "KILOMETERS", "distance": 16}, "iceThickness": {"unit": "MILLIMETERS", "thickness": 0}, "isDaytime": true, "relativeHumidity": 69, "uvIndex": 0, "thunderstormProbability": 0, "cloudCover": 72}, {"interval": {"startTime": "2026-04-12T18:00:00Z", "endTime": "2026-04-12T19:00:00Z"}, "displayDateTime": {"year": 2026, "month": 4, "day": 12, "hours": 21, "minutes": 0, "seconds": 0, "nanos": 0, "utcOffset": "10800s"}, "weatherCondition": {"iconBaseUri": "https://maps.gstatic.com/weather/v1/mostly_cloudy_night", "description": {"text": "Mostly cloudy", "languageCode": "en"}, "type": "MOSTLY_CLOUDY"}, "temperature": {"unit": "CELSIUS", "degrees": 2.5}, "feelsLikeTemperature": {"unit": "CELSIUS", "degrees": 1}, "dewPoint": {"unit": "CELSIUS", "degrees": -1.9}, "heatIndex": {"unit": "CELSIUS", "degrees": 2.5}, "windChill": {"unit": "CELSIUS", "degrees": 1}, "wetBulbTemperature": {"unit": "CELSIUS", "degrees": 0.6}, "precipitation": {"probability": {"type": "RAIN", "percent": 10}, "snowQpf": {"unit": "MILLIMETERS", "quantity": 0}, "qpf": {"unit": "MILLIMETERS", "quantity": 0}}, "airPressure": {"meanSeaLevelMillibars": 1010.61}, "wind": {"direction": {"cardinal": "EAST", "degrees": 97}, "speed": {"unit": "KILOMETERS_PER_HOUR", "value": 6}, "gust": {"unit": "KILOMETERS_PER_HOUR", "value": 18}}, "visibility": {"unit": "KILOMETERS", "distance": 16}, "iceThickness": {"unit": "MILLIMETERS", "thickness": 0}, "isDaytime": false, "relativeHumidity": 72, "uvIndex": 0, "thunderstormProbability": 0, "cloudCover": 73}, {"interval": {"startTime": "2026-04-12T19:00:00Z", "endTime": "2026-04-12T20:00:00Z"}, "displayDateTime": {"year": 2026, "month": 4, "day": 12, "hours": 22, "minutes": 0, "seconds": 0, "nanos": 0, "utcOffset": "10800s"}, "weatherCondition": {"iconBaseUri": "https://maps.gstatic.com/weather/v1/mostly_cloudy_night", "description": {"text": "Mostly cloudy", "languageCode": "en"}, "type": "MOSTLY_CLOUDY"}, "temperature": {"unit": "CELSIUS", "degrees": 2.3}, "feelsLikeTemperature": {"unit": "CELSIUS", "degrees": 1}, "dewPoint": {"unit": "CELSIUS", "degrees": -2.1}, "heatIndex": {"unit": "CELSIUS", "degrees": 2.3}, "windChill": {"unit": "CELSIUS", "degrees": 1}, "wetBulbTemperature": {"unit": "CELSIUS", "degrees": 0.4}, "precipitation": {"probability": {"type": "RAIN", "percent": 10}, "snowQpf": {"unit": "MILLIMETERS", "quantity": 0}, "qpf": {"unit": "MILLIMETERS", "quantity": 0}}, "airPressure": {"meanSeaLevelMillibars": 1010.59}, "wind": {"direction": {"cardinal": "EAST", "degrees": 99}, "speed": {"unit": "KILOMETERS_PER_HOUR", "value": 6}, "gust": {"unit": "KILOMETERS_PER_HOUR", "value": 18}}, "visibility": {"unit": "KILOMETERS", "distance": 16}, "iceThickness": {"unit": "MILLIMETERS", "thickness": 0}, "isDaytime": false, "relativeHumidity": 72, "uvIndex": 0, "thunderstormProbability": 0, "cloudCover": 72}, {"interval": {"startTime": "2026-04-12T20:00:00Z", "endTime": "2026-04-12T21:00:00Z"}, "displayDateTime": {"year": 2026, "month": 4, "day": 12, "hours": 23, "minutes": 0, "seconds": 0, "nanos": 0, "utcOffset": "10800s"}, "weatherCondition": {"iconBaseUri": "https://maps.gstatic.com/weather/v1/mostly_cloudy_night", "description": {"text": "Mostly cloudy", "languageCode": "en"}, "type": "MOSTLY_CLOUDY"}, "temperature": {"unit": "CELSIUS", "degrees": 2.3}, "feelsLikeTemperature": {"unit": "CELSIUS", "degrees": 0}, "dewPoint": {"unit": "CELSIUS", "degrees": -2.4}, "heatIndex": {"unit": "CELSIUS", "degrees": 2.3}, "windChill": {"unit": "CELSIUS", "degrees": 0}, "wetBulbTemperature": {"unit": "CELSIUS", "degrees": 0.2}, "precipitation": {"probability": {"type": "RAIN", "percent": 10}, "snowQpf": {"unit": "MILLIMETERS", "quantity": 0}, "qpf": {"unit": "MILLIMETERS", "quantity": 0}}, "airPressure": {"meanSeaLevelMillibars": 1010.52}, "wind": {"direction": {"cardinal": "EAST", "degrees": 100}, "speed": {"unit": "KILOMETERS_PER_HOUR", "value": 6}, "gust": {"unit": "KILOMETERS_PER_HOUR", "value": 18}}, "visibility": {"unit": "KILOMETERS", "distance": 16}, "iceThickness": {"unit": "MILLIMETERS", "thickness": 0}, "isDaytime": false, "relativeHumidity": 71, "uvIndex": 0, "thunderstormProbability": 0, "cloudCover": 71}, {"interval": {"startTime": "2026-04-12T21:00:00Z", "endTime": "2026-04-12T22:00:00Z"}, "displayDateTime": {"year": 2026, "month": 4, "day": 13, "hours": 0, "minutes": 0, "seconds": 0, "nanos": 0, "utcOffset": "10800s"}, "weatherCondition": {"iconBaseUri": "https://maps.gstatic.com/weather/v1/mostly_cloudy_night", "description": {"text": "Mostly cloudy", "languageCode": "en"}, "type": "MOSTLY_CLOUDY"}, "temperature": {"unit": "CELSIUS", "degrees": 2.3}, "feelsLikeTemperature": {"unit": "CELSIUS", "degrees": 0}, "dewPoint": {"unit": "CELSIUS", "degrees": -2.7}, "heatIndex": {"unit": "CELSIUS", "degrees": 2.3}, "windChill": {"unit": "CELSIUS", "degrees": 0}, "wetBulbTemperature": {"unit": "CELSIUS", "degrees": 0.2}, "precipitation": {"probability": {"type": "RAIN", "percent": 10}, "snowQpf": {"unit": "MILLIMETERS", "quantity": 0}, "qpf": {"unit": "MILLIMETERS", "quantity": 0}}, "airPressure": {"meanSeaLevelMillibars": 1010.32}, "wind": {"direction": {"cardinal": "EAST", "degrees": 101}, "speed": {"unit": "KILOMETERS_PER_HOUR", "value": 6}, "gust": {"unit": "KILOMETERS_PER_HOUR", "value": 18}}, "visibility": {"unit": "KILOMETERS", "distance": 16}, "iceThickness": {"unit": "MILLIMETERS", "thickness": 0}, "isDaytime": false, "relativeHumidity": 69, "uvIndex": 0, "thunderstormProbability": 0, "cloudCover": 70}, {"interval": {"startTime": "2026-04-12T22:00:00Z", "endTime": "2026-04-12T23:00:00Z"}, "displayDateTime": {"year": 2026, "month": 4, "day": 13, "hours": 1, "minutes": 0, "seconds": 0, "nanos": 0, "utcOffset": "10800s"}, "weatherCondition": {"iconBaseUri": "https://maps.gstatic.com/weather/v1/mostly_cloudy_night", "description": {"text": "Mostly cloudy", "languageCode": "en"}, "type": "MOSTLY_CLOUDY"}, "temperature": {"unit": "CELSIUS", "degrees": 2.3}, "feelsLikeTemperature": {"unit": "CELSIUS", "degrees": 1}, "dewPoint": {"unit": "CELSIUS", "degrees": -2.9}, "heatIndex": {"unit": "CELSIUS", "degrees": 2.3}, "windChill": {"unit": "CELSIUS", "degrees": 1}, "wetBulbTemperature": {"unit": "CELSIUS", "degrees": 0.1}, "precipitation": {"probability": {"type": "RAIN", "percent": 10}, "snowQpf": {"unit": "MILLIMETERS", "quantity": 0}, "qpf": {"unit": "MILLIMETERS", "quantity": 0}}, "airPressure": {"meanSeaLevelMillibars": 1010.09}, "wind": {"direction": {"cardinal": "EAST", "degrees": 101}, "speed": {"unit": "KILOMETERS_PER_HOUR", "value": 6}, "gust": {"unit": "KILOMETERS_PER_HOUR", "value": 18}}, "visibility": {"unit": "KILOMETERS", "distance": 16}, "iceThickness": {"unit": "MILLIMETERS", "thickness": 0}, "isDaytime": false, "relativeHumidity": 68, "uvIndex": 0, "thunderstormProbability": 0, "cloudCover": 70}, {"interval": {"startTime": "2026-04-12T23:00:00Z", "endTime": "2026-04-13T00:00:00Z"}, "displayDateTime": {"year": 2026, "month": 4, "day": 13, "hours": 2, "minutes": 0, "seconds": 0, "nanos": 0, "utcOffset": "10800s"}, "weatherCondition": {"iconBaseUri": "https://maps.gstatic.com/weather/v1/mostly_cloudy_night", "description": {"text": "Mostly cloudy", "languageCode": "en"}, "type": "MOSTLY_CLOUDY"}, "temperature": {"unit": "CELSIUS", "degrees": 2.3}, "feelsLikeTemperature": {"unit": "CELSIUS", "degrees": 1}, "dewPoint": {"unit": "CELSIUS", "degrees": -3.2}, "heatIndex": {"unit": "CELSIUS", "degrees": 2.3}, "windChill": {"unit": "CELSIUS", "degrees": 1}, "wetBulbTemperature": {"unit": "CELSIUS", "degrees": 0}, "precipitation": {"probability": {"type": "RAIN", "percent": 10}, "snowQpf": {"unit": "MILLIMETERS", "quantity": 0}, "qpf": {"unit": "MILLIMETERS", "quantity": 0}}, "airPressure": {"meanSeaLevelMillibars": 1009.51}, "wind": {"direction": {"cardinal": "EAST", "degrees": 101}, "speed": {"unit": "KILOMETERS_PER_HOUR", "value": 6}, "gust": {"unit": "KILOMETERS_PER_HOUR", "value": 18}}, "visibility": {"unit": "KILOMETERS", "distance": 16}, "iceThickness": {"unit": "MILLIMETERS", "thickness": 0}, "isDaytime": false, "relativeHumidity": 67, "uvIndex": 0, "thunderstormProbability": 0, "cloudCover": 70}, {"interval": {"startTime": "2026-04-13T00:00:00Z", "endTime": "2026-04-13T01:00:00Z"}, "displayDateTime": {"year": 2026, "month": 4, "day": 13, "hours": 3, "minutes": 0, "seconds": 0, "nanos": 0, "utcOffset": "10800s"}, "weatherCondition": {"iconBaseUri": "https://maps.gstatic.com/weather/v1/mostly_cloudy_night", "description": {"text": "Mostly cloudy", "languageCode": "en"}, "type": "MOSTLY_CLOUDY"}, "temperature": {"unit": "CELSIUS", "degrees": 2.3}, "feelsLikeTemperature": {"unit": "CELSIUS", "degrees": 1}, "dewPoint": {"unit": "CELSIUS", "degrees": -3.4}, "heatIndex": {"unit": "CELSIUS", "degrees": 2.3}, "windChill": {"unit": "CELSIUS", "degrees": 1}, "wetBulbTemperature": {"unit": "CELSIUS", "degrees": 0}, "precipitation": {"probability": {"type": "RAIN", "percent": 10}, "snowQpf": {"unit": "MILLIMETERS", "quantity": 0}, "qpf": {"unit": "MILLIMETERS", "quantity": 0}}, "airPressure": {"meanSeaLevelMillibars": 1009.26}, "wind": {"direction": {"cardinal": "EAST", "degrees": 102}, "speed": {"unit": "KILOMETERS_PER_HOUR", "value": 5}, "gust": {"unit": "KILOMETERS_PER_HOUR", "value": 16}}, "visibility": {"unit": "KILOMETERS", "distance": 16}, "iceThickness": {"unit": "MILLIMETERS", "thickness": 0}, "isDaytime": false, "relativeHumidity": 65, "uvIndex": 0, "thunderstormProbability": 0, "cloudCover": 70}, {"interval": {"startTime": "2026-04-13T01:00:00Z", "endTime": "2026-04-13T02:00:00Z"}, "displayDateTime": {"year": 2026, "month": 4, "day": 13, "hours": 4, "minutes": 0, "seconds": 0, "nanos": 0, "utcOffset": "10800s"}, "weatherCondition": {"iconBaseUri": "https://maps.gstatic.com/weather/v1/mostly_cloudy_night", "description": {"text": "Mostly cloudy", "languageCode": "en"}, "type": "MOSTLY_CLOUDY"}, "temperature": {"unit": "CELSIUS", "degrees": 2.3}, "feelsLikeTemperature": {"unit": "CELSIUS", "degrees": 1}, "dewPoint": {"unit": "CELSIUS", "degrees": -3.7}, "heatIndex": {"unit": "CELSIUS", "degrees": 2.3}, "windChill": {"unit": "CELSIUS", "degrees": 1}, "wetBulbTemperature": {"unit": "CELSIUS", "degrees": -0.1}, "precipitation": {"probability": {"type": "RAIN", "percent": 10}, "snowQpf": {"unit": "MILLIMETERS", "quantity": 0}, "qpf": {"unit": "MILLIMETERS", "quantity": 0.02}}, "airPressure": {"meanSeaLevelMillibars": 1008.65}, "wind": {"direction": {"cardinal": "EAST_SOUTHEAST", "degrees": 103}, "speed": {"unit": "KILOMETERS_PER_HOUR", "value": 5}, "gust": {"unit": "KILOMETERS_PER_HOUR", "value": 16}}, "visibility": {"unit": "KILOMETERS", "distance": 16}, "iceThickness": {"unit": "MILLIMETERS", "thickness": 0}, "isDaytime": false, "relativeHumidity": 64, "uvIndex": 0, "thunderstormProbability": 0, "cloudCover": 70}, {"interval": {"startTime": "2026-04-13T02:00:00Z", "endTime": "2026-04-13T03:00:00Z"}, "displayDateTime": {"year": 2026, "month": 4, "day": 13, "hours": 5, "minutes": 0, "seconds": 0, "nanos": 0, "utcOffset": "10800s"}, "weatherCondition": {"iconBaseUri": "https://maps.gstatic.com/weather/v1/mostly_cloudy_night", "description": {"text": "Mostly cloudy", "languageCode": "en"}, "type": "MOSTLY_CLOUDY"}, "temperature": {"unit": "CELSIUS", "degrees": 2.2}, "feelsLikeTemperature": {"unit": "CELSIUS", "degrees": 1}, "dewPoint": {"unit": "CELSIUS", "degrees": -3.9}, "heatIndex": {"unit": "CELSIUS", "degrees": 2.2}, "windChill": {"unit": "CELSIUS", "degrees": 1}, "wetBulbTemperature": {"unit": "CELSIUS", "degrees": -0.3}, "precipitation": {"probability": {"type": "RAIN", "percent": 10}, "snowQpf": {"unit": "MILLIMETERS", "quantity": 0}, "qpf": {"unit": "MILLIMETERS", "quantity": 0.02}}, "airPressure": {"meanSeaLevelMillibars": 1008.14}, "wind": {"direction": {"cardinal": "EAST_SOUTHEAST", "degrees": 103}, "speed": {"unit": "KILOMETERS_PER_HOUR", "value": 6}, "gust": {"unit": "KILOMETERS_PER_HOUR", "value": 16}}, "visibility": {"unit": "KILOMETERS", "distance": 16}, "iceThickness": {"unit": "MILLIMETERS", "thickness": 0}, "isDaytime": false, "relativeHumidity": 64, "uvIndex": 0, "thunderstormProbability": 0, "cloudCover": 70}, {"interval": {"startTime": "2026-04-13T03:00:00Z", "endTime": "2026-04-13T04:00:00Z"}, "displayDateTime": {"year": 2026, "month": 4, "day": 13, "hours": 6, "minutes": 0, "seconds": 0, "nanos": 0, "utcOffset": "10800s"}, "weatherCondition": {"iconBaseUri": "https://maps.gstatic.com/weather/v1/mostly_cloudy_night", "description": {"text": "Mostly cloudy", "languageCode": "en"}, "type": "MOSTLY_CLOUDY"}, "temperature": {"unit": "CELSIUS", "degrees": 2.3}, "feelsLikeTemperature": {"unit": "CELSIUS", "degrees": 1}, "dewPoint": {"unit": "CELSIUS", "degrees": -4}, "heatIndex": {"unit": "CELSIUS", "degrees": 2.3}, "windChill": {"unit": "CELSIUS", "degrees": 1}, "wetBulbTemperature": {"unit": "CELSIUS", "degrees": -0.2}, "precipitation": {"probability": {"type": "RAIN", "percent": 10}, "snowQpf": {"unit": "MILLIMETERS", "quantity": 0}, "qpf": {"unit": "MILLIMETERS", "quantity": 0.02}}, "airPressure": {"meanSeaLevelMillibars": 1007.82}, "wind": {"direction": {"cardinal": "EAST_SOUTHEAST", "degrees": 104}, "speed": {"unit": "KILOMETERS_PER_HOUR", "value": 6}, "gust": {"unit": "KILOMETERS_PER_HOUR", "value": 16}}, "visibility": {"unit": "KILOMETERS", "distance": 16}, "iceThickness": {"unit": "MILLIMETERS", "thickness": 0}, "isDaytime": false, "relativeHumidity": 63, "uvIndex": 0, "thunderstormProbability": 0, "cloudCover": 71}, {"interval": {"startTime": "2026-04-13T04:00:00Z", "endTime": "2026-04-13T05:00:00Z"}, "displayDateTime": {"year": 2026, "month": 4, "day": 13, "hours": 7, "minutes": 0, "seconds": 0, "nanos": 0, "utcOffset": "10800s"}, "weatherCondition": {"iconBaseUri": "https://maps.gstatic.com/weather/v1/mostly_cloudy", "description": {"text": "Mostly cloudy", "languageCode": "en"}, "type": "MOSTLY_CLOUDY"}, "temperature": {"unit": "CELSIUS", "degrees": 2.6}, "feelsLikeTemperature": {"unit": "CELSIUS", "degrees": 1}, "dewPoint": {"unit": "CELSIUS", "degrees": -3.9}, "heatIndex": {"unit": "CELSIUS", "degrees": 2.6}, "windChill": {"unit": "CELSIUS", "degrees": 1}, "wetBulbTemperature": {"unit": "CELSIUS", "degrees": 0}, "precipitation": {"probability": {"type": "RAIN", "percent": 10}, "snowQpf": {"unit": "MILLIMETERS", "quantity": 0}, "qpf": {"unit": "MILLIMETERS", "quantity": 0.02}}, "airPressure": {"meanSeaLevelMillibars": 1007.76}, "wind": {"direction": {"cardinal": "EAST_SOUTHEAST", "degrees": 104}, "speed": {"unit": "KILOMETERS_PER_HOUR", "value": 6}, "gust": {"unit": "KILOMETERS_PER_HOUR", "value": 18}}, "visibility": {"unit": "KILOMETERS", "distance": 16}, "iceThickness": {"unit": "MILLIMETERS", "thickness": 0}, "isDaytime": true, "relativeHumidity": 62, "uvIndex": 0, "thunderstormProbability": 0, "cloudCover": 77}, {"interval": {"startTime": "2026-04-13T05:00:00Z", "endTime": "2026-04-13T06:00:00Z"}, "displayDateTime": {"year": 2026, "month": 4, "day": 13, "hours": 8, "minutes": 0, "seconds": 0, "nanos": 0, "utcOffset": "10800s"}, "weatherCondition": {"iconBaseUri": "https://maps.gstatic.com/weather/v1/mostly_cloudy", "description": {"text": "Mostly cloudy", "languageCode": "en"}, "type": "MOSTLY_CLOUDY"}, "temperature": {"unit": "CELSIUS", "degrees": 3.5}, "feelsLikeTemperature": {"unit": "CELSIUS", "degrees": 2}, "dewPoint": {"unit": "CELSIUS", "degrees": -3.6}, "heatIndex": {"unit": "CELSIUS", "degrees": 3.5}, "windChill": {"unit": "CELSIUS", "degrees": 2}, "wetBulbTemperature": {"unit": "CELSIUS", "degrees": 0.5}, "precipitation": {"probability": {"type": "RAIN", "percent": 10}, "snowQpf": {"unit": "MILLIMETERS", "quantity": 0}, "qpf": {"unit": "MILLIMETERS", "quantity": 0.02}}, "airPressure": {"meanSeaLevelMillibars": 1007.83}, "wind": {"direction": {"cardinal": "EAST_SOUTHEAST", "degrees": 105}, "speed": {"unit": "KILOMETERS_PER_HOUR", "value": 6}, "gust": {"unit": "KILOMETERS_PER_HOUR", "value": 18}}, "visibility": {"unit": "KILOMETERS", "distance": 16}, "iceThickness": {"unit": "MILLIMETERS", "thickness": 0}, "isDaytime": true, "relativeHumidity": 59, "uvIndex": 0, "thunderstormProbability": 0, "cloudCover": 84}], "timeZone": {"id": "Europe/Athens", "version": ""}, "nextPageToken": "ChcKEgmzlgLS_vlCQBGxbVFmgzA2QBDwARDAARjAASIMCOD7x84GEPOm8u8BKg1FdXJvcGUvQXRoZW5z"}