{"forecastHours": [{"interval": {"startTime": "2026-04-10T21:00:00Z", "endTime": "2026-04-10T22:00:00Z"}, "displayDateTime": {"year": 2026, "month": 4, "day": 11, "hours": 0, "minutes": 0, "seconds": 0, "nanos": 0, "utcOffset": "10800s"}, "weatherCondition": {"iconBaseUri": "https://maps.gstatic.com/weather/v1/wintry_mix", "description": {"text": "Rain and snow", "languageCode": "en"}, "type": "RAIN_AND_SNOW"}, "temperature": {"unit": "CELSIUS", "degrees": 1.2}, "feelsLikeTemperature": {"unit": "CELSIUS", "degrees": -1}, "dewPoint": {"unit": "CELSIUS", "degrees": -0.3}, "heatIndex": {"unit": "CELSIUS", "degrees": 1.2}, "windChill": {"unit": "CELSIUS", "degrees": -1}, "wetBulbTemperature": {"unit": "CELSIUS", "degrees": 0.5}, "precipitation": {"probability": {"type": "RAIN_AND_SNOW", "percent": 65}, "snowQpf": {"unit": "MILLIMETERS", "quantity": 9.79}, "qpf": {"unit": "MILLIMETERS", "quantity": 1.59}}, "airPressure": {"meanSeaLevelMillibars": 1021.97}, "wind": {"direction": {"cardinal": "EAST_NORTHEAST", "degrees": 72}, "speed": {"unit": "KILOMETERS_PER_HOUR", "value": 6}, "gust": {"unit": "KILOMETERS_PER_HOUR", "value": 13}}, "visibility": {"unit": "KILOMETERS", "distance": 13}, "iceThickness": {"unit": "MILLIMETERS", "thickness": 0}, "isDaytime": false, "relativeHumidity": 89, "uvIndex": 0, "thunderstormProbability": 10, "cloudCover": 71}, {"interval": {"startTime": "2026-04-10T22:00:00Z", "endTime": "2026-04-10T23:00:00Z"}, "displayDateTime": {"year": 2026, "month": 4, "day": 11, "hours": 1, "minutes": 0, "seconds": 0, "nanos": 0, "utcOffset": "10800s"}, "weatherCondition": {"iconBaseUri": "https://maps.gstatic.com/weather/v1/wintry_mix", "description": {"text": "Rain and snow", "languageCode": "en"}, "type": "RAIN_AND_SNOW"}, "temperature": {"unit": "CELSIUS", "degrees": 1}, "feelsLikeTemperature": {"unit": "CELSIUS", "degrees": -1}, "dewPoint": {"unit": "CELSIUS", "degrees": -0.7}, "heatIndex": {"unit": "CELSIUS", "degrees": 1}, "windChill": {"unit": "CELSIUS", "degrees": -1}, "wetBulbTemperature": {"unit": "CELSIUS", "degrees": 0.3}, "precipitation": {"probability": {"type": "RAIN_AND_SNOW", "percent": 65}, "snowQpf": {"unit": "MILLIMETERS", "quantity": 10.47}, "qpf": {"unit": "MILLIMETERS", "quantity": 1.59}}, "airPressure": {"meanSeaLevelMillibars": 1022.02}, "wind": {"direction": {"cardinal": "EAST", "degrees": 80}, "speed": {"unit": "KILOMETERS_PER_HOUR", "value": 6}, "gust": {"unit": "KILOMETERS_PER_HOUR", "value": 11}}, "visibility": {"unit": "KILOMETERS", "distance": 14}, "iceThickness": {"unit": "MILLIMETERS", "thickness": 0}, "isDaytime": false, "relativeHumidity": 88, "uvIndex": 0, "thunderstormProbability": 10, "cloudCover": 71}, {"interval": {"startTime": "2026-04-10T23:00:00Z", "endTime": "2026-04-11T00:00:00Z"}, "displayDateTime": {"year": 2026, "month": 4, "day": 11, "hours": 2, "minutes": 0, "seconds": 0, "nanos": 0, "utcOffset": "10800s"}, "weatherCondition": {"iconBaseUri": "https://maps.gstatic.com/weather/v1/flurries", "description": {"text": "Light snow", "languageCode": "en"}, "type": "LIGHT_SNOW"}, "temperature": {"unit": "CELSIUS", "degrees": 0.8}, "feelsLikeTemperature": {"unit": "CELSIUS", "degrees": -1}, "dewPoint": {"unit": "CELSIUS", "degrees": -0.9}, "heatIndex": {"unit": "CELSIUS", "degrees": 0.8}, "windChill": {"unit": "CELSIUS", "degrees": -1}, "wetBulbTemperature": {"unit": "CELSIUS", "degrees": 0}, "precipitation": {"probability": {"type": "SNOW", "percent": 65}, "snowQpf": {"unit": "MILLIMETERS", "quantity": 11.16}, "qpf": {"unit": "MILLIMETERS", "quantity": 1.59}}, "airPressure": {"meanSeaLevelMillibars": 1021.91}, "wind": {"direction": {"cardinal": "EAST", "degrees": 83}, "speed": {"unit": "KILOMETERS_PER_HOUR", "value": 6}, "gust": {"unit": "KILOMETERS_PER_HOUR", "value": 11}}, "visibility": {"unit": "KILOMETERS", "distance": 14}, "iceThickness": {"unit": "MILLIMETERS", "thickness": 0}, "isDaytime": false, "relativeHumidity": 88, "uvIndex": 0, "thunderstormProbability": 10, "cloudCover": 71}, {"interval": {"startTime": "2026-04-11T00:00:00Z", "endTime": "2026-04-11T01:00:00Z"}, "displayDateTime": {"year": 2026, "month": 4, "day": 11, "hours": 3, "minutes": 0, "seconds": 0, "nanos": 0, "utcOffset": "10800s"}, "weatherCondition": {"iconBaseUri": "https://maps.gstatic.com/weather/v1/flurries", "description": {"text": "Light snow", "languageCode": "en"}, "type": "LIGHT_SNOW"}, "temperature": {"unit": "CELSIUS", "degrees": 0.3}, "feelsLikeTemperature": {"unit": "CELSIUS", "degrees": -2}, "dewPoint": {"unit": "CELSIUS", "degrees": -1.2}, "heatIndex": {"unit": "CELSIUS", "degrees": 0.3}, "windChill": {"unit": "CELSIUS", "degrees": -2}, "wetBulbTemperature": {"unit": "CELSIUS", "degrees": -0.3}, "precipitation": {"probability": {"type": "SNOW", "percent": 65}, "snowQpf": {"unit": "MILLIMETERS", "quantity": 11.82}, "qpf": {"unit": "MILLIMETERS", "quantity": 1.59}}, "airPressure": {"meanSeaLevelMillibars": 1021.6}, "wind": {"direction": {"cardinal": "EAST", "degrees": 86}, "speed": {"unit": "KILOMETERS_PER_HOUR", "value": 6}, "gust": {"unit": "KILOMETERS_PER_HOUR", "value": 11}}, "visibility": {"unit": "KILOMETERS", "distance": 13}, "iceThickness": {"unit": "MILLIMETERS", "thickness": 0.04}, "isDaytime": false, "relativeHumidity": 89, "uvIndex": 0, "thunderstormProbability": 10, "cloudCover": 71}, {"interval": {"startTime": "2026-04-11T01:00:00Z", "endTime": "2026-04-11T02:00:00Z"}, "displayDateTime": {"year": 2026, "month": 4, "day": 11, "hours": 4, "minutes": 0, "seconds": 0, "nanos": 0, "utcOffset": "10800s"}, "weatherCondition": {"iconBaseUri": "https://maps.gstatic.com/weather/v1/flurries", "description": {"text": "Light snow", "languageCode": "en"}, "type": "LIGHT_SNOW"}, "temperature": {"unit": "CELSIUS", "degrees": 0}, "feelsLikeTemperature": {"unit": "CELSIUS", "degrees": -2}, "dewPoint": {"unit": "CELSIUS", "degrees": -1.3}, "heatIndex": {"unit": "CELSIUS", "degrees": 0}, "windChill": {"unit": "CELSIUS", "degrees": -2}, "wetBulbTemperature": {"unit": "CELSIUS", "degrees": -0.5}, "precipitation": {"probability": {"type": "SNOW", "percent": 65}, "snowQpf": {"unit": "MILLIMETERS", "quantity": 12.33}, "qpf": {"unit": "MILLIMETERS", "quantity": 1.53}}, "airPressure": {"meanSeaLevelMillibars": 1021.59}, "wind": {"direction": {"cardinal": "EAST", "degrees": 83}, "speed": {"unit": "KILOMETERS_PER_HOUR", "value": 6}, "gust": {"unit": "KILOMETERS_PER_HOUR", "value": 13}}, "visibility": {"unit": "KILOMETERS", "distance": 8}, "iceThickness": {"unit": "MILLIMETERS", "thickness": 0.03}, "isDaytime": false, "relativeHumidity": 91, "uvIndex": 0, "thunderstormProbability": 10, "cloudCover": 71}, {"interval": {"startTime": "2026-04-11T02:00:00Z", "endTime": "2026-04-11T03:00:00Z"}, "displayDateTime": {"year": 2026, "month": 4, "day": 11, "hours": 5, "minutes": 0, "seconds": 0, "nanos": 0, "utcOffset": "10800s"}, "weatherCondition": {"iconBaseUri": "https://maps.gstatic.com/weather/v1/snow_showers", "description": {"text": "Snow", "languageCode": "en"}, "type": "SNOW"}, "temperature": {"unit": "CELSIUS", "degrees": -0.2}, "feelsLikeTemperature": {"unit": "CELSIUS", "degrees": -2}, "dewPoint": {"unit": "CELSIUS", "degrees": -1.4}, "heatIndex": {"unit": "CELSIUS", "degrees": -0.2}, "windChill": {"unit": "CELSIUS", "degrees": -2}, "wetBulbTemperature": {"unit": "CELSIUS", "degrees": -0.6}, "precipitation": {"probability": {"type": "SNOW", "percent": 65}, "snowQpf": {"unit": "MILLIMETERS", "quantity": 13.28}, "qpf": {"unit": "MILLIMETERS", "quantity": 1.53}}, "airPressure": {"meanSeaLevelMillibars": 1021.55}, "wind": {"direction": {"cardinal": "EAST", "degrees": 79}, "speed": {"unit": "KILOMETERS_PER_HOUR", "value": 6}, "gust": {"unit": "KILOMETERS_PER_HOUR", "value": 13}}, "visibility": {"unit": "KILOMETERS", "distance": 8}, "iceThickness": {"unit": "MILLIMETERS", "thickness": 0.04}, "isDaytime": false, "relativeHumidity": 91, "uvIndex": 0, "thunderstormProbability": 10, "cloudCover": 71}, {"interval": {"startTime": "2026-04-11T03:00:00Z", "endTime": "2026-04-11T04:00:00Z"}, "displayDateTime": {"year": 2026, "month": 4, "day": 11, "hours": 6, "minutes": 0, "seconds": 0, "nanos": 0, "utcOffset": "10800s"}, "weatherCondition": {"iconBaseUri": "https://maps.gstatic.com/weather/v1/snow_showers", "description": {"text": "Snow", "languageCode": "en"}, "type": "SNOW"}, "temperature": {"unit": "CELSIUS", "degrees": -0.2}, "feelsLikeTemperature": {"unit": "CELSIUS", "degrees": -2}, "dewPoint": {"unit": "CELSIUS", "degrees": -1.4}, "heatIndex": {"unit": "CELSIUS", "degrees": -0.2}, "windChill": {"unit": "CELSIUS", "degrees": -2}, "wetBulbTemperature": {"unit": "CELSIUS", "degrees": -0.7}, "precipitation": {"probability": {"type": "SNOW", "percent": 65}, "snowQpf": {"unit": "MILLIMETERS", "quantity": 14.22}, "qpf": {"unit": "MILLIMETERS", "quantity": 1.53}}, "airPressure": {"meanSeaLevelMillibars": 1021.66}, "wind": {"direction": {"cardinal": "EAST_NORTHEAST", "degrees": 73}, "speed": {"unit": "KILOMETERS_PER_HOUR", "value": 6}, "gust": {"unit": "KILOMETERS_PER_HOUR", "value": 13}}, "visibility": {"unit": "KILOMETERS", "distance": 8}, "iceThickness": {"unit": "MILLIMETERS", "thickness": 0.04}, "isDaytime": false, "relativeHumidity": 91, "uvIndex": 0, "thunderstormProbability": 10, "cloudCover": 71}, {"interval": {"startTime": "2026-04-11T04:00:00Z", "endTime": "2026-04-11T05:00:00Z"}, "displayDateTime": {"year": 2026, "month": 4, "day": 11, "hours": 7, "minutes": 0, "seconds": 0, "nanos": 0, "utcOffset": "10800s"}, "weatherCondition": {"iconBaseUri": "https://maps.gstatic.com/weather/v1/snow_showers", "description": {"text": "Snow", "languageCode": "en"}, "type": "SNOW"}, "temperature": {"unit": "CELSIUS", "degrees": -0.1}, "feelsLikeTemperature": {"unit": "CELSIUS", "degrees": -2}, "dewPoint": {"unit": "CELSIUS", "degrees": -1.4}, "heatIndex": {"unit": "CELSIUS", "degrees": -0.1}, "windChill": {"unit": "CELSIUS", "degrees": -2}, "wetBulbTemperature": {"unit": "CELSIUS", "degrees": -0.6}, "precipitation": {"probability": {"type": "SNOW", "percent": 65}, "snowQpf": {"unit": "MILLIMETERS", "quantity": 15.13}, "qpf": {"unit": "MILLIMETERS", "quantity": 1.53}}, "airPressure": {"meanSeaLevelMillibars": 1022.03}, "wind": {"direction": {"cardinal": "EAST_NORTHEAST", "degrees": 60}, "speed": {"unit": "KILOMETERS_PER_HOUR", "value": 5}, "gust": {"unit": "KILOMETERS_PER_HOUR", "value": 14}}, "visibility": {"unit": "KILOMETERS", "distance": 8}, "iceThickness": {"unit": "MILLIMETERS", "thickness": 0.03}, "isDaytime": true, "relativeHumidity": 90, "uvIndex": 0, "thunderstormProbability": 10, "cloudCover": 77}, {"interval": {"startTime": "2026-04-11T05:00:00Z", "endTime": "2026-04-11T06:00:00Z"}, "displayDateTime": {"year": 2026, "month": 4, "day": 11, "hours": 8, "minutes": 0, "seconds": 0, "nanos": 0, "utcOffset": "10800s"}, "weatherCondition": {"iconBaseUri": "https://maps.gstatic.com/weather/v1/snow_showers", "description": {"text": "Snow", "languageCode": "en"}, "type": "SNOW"}, "temperature": {"unit": "CELSIUS", "degrees": 0.9}, "feelsLikeTemperature": {"unit": "CELSIUS", "degrees": -1}, "dewPoint": {"unit": "CELSIUS", "degrees": -1.4}, "heatIndex": {"unit": "CELSIUS", "degrees": 0.9}, "windChill": {"unit": "CELSIUS", "degrees": -1}, "wetBulbTemperature": {"unit": "CELSIUS", "degrees": -0.1}, "precipitation": {"probability": {"type": "SNOW", "percent": 65}, "snowQpf": {"unit": "MILLIMETERS", "quantity": 16.01}, "qpf": {"unit": "MILLIMETERS", "quantity": 1.53}}, "airPressure": {"meanSeaLevelMillibars": 1022.38}, "wind": {"direction": {"cardinal": "NORTHEAST", "degrees": 40}, "speed": {"unit": "KILOMETERS_PER_HOUR", "value": 5}, "gust": {"unit": "KILOMETERS_PER_HOUR", "value": 14}}, "visibility": {"unit": "KILOMETERS", "distance": 14}, "iceThickness": {"unit": "MILLIMETERS", "thickness": 0.03}, "isDaytime": true, "relativeHumidity": 84, "uvIndex": 0, "thunderstormProbability": 10, "cloudCover": 82}, {"interval": {"startTime": "2026-04-11T06:00:00Z", "endTime": "2026-04-11T07:00:00Z"}, "displayDateTime": {"year": 2026, "month": 4, "day": 11, "hours": 9, "minutes": 0, "seconds": 0, "nanos": 0, "utcOffset": "10800s"}, "weatherCondition": {"iconBaseUri": "https://maps.gstatic.com/weather/v1/snow_showers", "description": {"text": "Snow", "languageCode": "en"}, "type": "SNOW"}, "temperature": {"unit": "CELSIUS", "degrees": 2.7}, "feelsLikeTemperature": {"unit": "CELSIUS", "degrees": 1}, "dewPoint": {"unit": "CELSIUS", "degrees": -1.5}, "heatIndex": {"unit": "CELSIUS", "degrees": 2.7}, "windChill": {"unit": "CELSIUS", "degrees": 1}, "wetBulbTemperature": {"unit": "CELSIUS", "degrees": 0.9}, "precipitation": {"probability": {"type": "SNOW", "percent": 65}, "snowQpf": {"unit": "MILLIMETERS", "quantity": 16.92}, "qpf": {"unit": "MILLIMETERS", "quantity": 1.53}}, "airPressure": {"meanSeaLevelMillibars": 1022.11}, "wind": {"direction": {"cardinal": "NORTH_NORTHEAST", "degrees": 15}, "speed": {"unit": "KILOMETERS_PER_HOUR", "value": 6}, "gust": {"unit": "KILOMETERS_PER_HOUR", "value": 18}}, "visibility": {"unit": "KILOMETERS", "distance": 16}, "iceThickness": {"unit": "MILLIMETERS", "thickness": 0}, "isDaytime": true, "relativeHumidity": 73, "uvIndex": 0, "thunderstormProbability": 0, "cloudCover": 88}, {"interval": {"startTime": "2026-04-11T07:00:00Z", "endTime": "2026-04-11T08:00:00Z"}, "displayDateTime": {"year": 2026, "month": 4, "day": 11, "hours": 10, "minutes": 0, "seconds": 0, "nanos": 0, "utcOffset": "10800s"}, "weatherCondition": {"iconBaseUri": "https://maps.gstatic.com/weather/v1/showers", "description": {"text": "Rain", "languageCode": "en"}, "type": "RAIN"}, "temperature": {"unit": "CELSIUS", "degrees": 4.1}, "feelsLikeTemperature": {"unit": "CELSIUS", "degrees": 2}, "dewPoint": {"unit": "CELSIUS", "degrees": -1.6}, "heatIndex": {"unit": "CELSIUS", "degrees": 4.1}, "windChill": {"unit": "CELSIUS", "degrees": 2}, "wetBulbTemperature": {"unit": "CELSIUS", "degrees": 1.6}, "precipitation": {"probability": {"type": "RAIN", "percent": 70}, "snowQpf": {"unit": "MILLIMETERS", "quantity": 0}, "qpf": {"unit": "MILLIMETERS", "quantity": 2.02}}, "airPressure": {"meanSeaLevelMillibars": 1022.41}, "wind": {"direction": {"cardinal": "NORTH", "degrees": 0}, "speed": {"unit": "KILOMETERS_PER_HOUR", "value": 8}, "gust": {"unit": "KILOMETERS_PER_HOUR", "value": 24}}, "visibility": {"unit": "KILOMETERS", "distance": 16}, "iceThickness": {"unit": "MILLIMETERS", "thickness": 0}, "isDaytime": true, "relativeHumidity": 66, "uvIndex": 0, "thunderstormProbability": 0, "cloudCover": 92}, {"interval": {"startTime": "2026-04-11T08:00:00Z", "endTime": "2026-04-11T09:00:00Z"}, "displayDateTime": {"year": 2026, "month": 4, "day": 11, "hours": 11, "minutes": 0, "seconds": 0, "nanos": 0, "utcOffset": "10800s"}, "weatherCondition": {"iconBaseUri": "https://maps.gstatic.com/weather/v1/showers", "description": {"text": "Rain", "languageCode": "en"}, "type": "RAIN"}, "temperature": {"unit": "CELSIUS", "degrees": 5.2}, "feelsLikeTemperature": {"unit": "CELSIUS", "degrees": 3}, "dewPoint": {"unit": "CELSIUS", "degrees": -1.8}, "heatIndex": {"unit": "CELSIUS", "degrees": 5.2}, "windChill": {"unit": "CELSIUS", "degrees": 3}, "wetBulbTemperature": {"unit": "CELSIUS", "degrees": 2.1}, "precipitation": {"probability": {"type": "RAIN", "percent": 70}, "snowQpf": {"unit": "MILLIMETERS", "quantity": 0}, "qpf": {"unit": "MILLIMETERS", "quantity": 2.02}}, "airPressure": {"meanSeaLevelMillibars": 1022.54}, "wind": {"direction": {"cardinal": "NORTH", "degrees": 354}, "speed": {"unit": "KILOMETERS_PER_HOUR", "value": 10}, "gust": {"unit": "KILOMETERS_PER_HOUR", "value": 29}}, "visibility": {"unit": "KILOMETERS", "distance": 16}, "iceThickness": {"unit": "MILLIMETERS", "thickness": 0}, "isDaytime": true, "relativeHumidity": 60, "uvIndex": 1, "thunderstormProbability": 0, "cloudCover": 96}, {"interval": {"startTime": "2026-04-11T09:00:00Z", "endTime": "2026-04-11T10:00:00Z"}, "displayDateTime": {"year": 2026, "month": 4, "day": 11, "hours": 12, "minutes": 0, "seconds": 0, "nanos": 0, "utcOffset": "10800s"}, "weatherCondition": {"iconBaseUri": "https://maps.gstatic.com/weather/v1/showers", "description": {"text": "Rain", "languageCode": "en"}, "type": "RAIN"}, "temperature": {"unit": "CELSIUS", "degrees": 6.1}, "feelsLikeTemperature": {"unit": "CELSIUS", "degrees": 4}, "dewPoint": {"unit": "CELSIUS", "degrees": -1.9}, "heatIndex": {"unit": "CELSIUS", "degrees": 6.1}, "windChill": {"unit": "CELSIUS", "degrees": 4}, "wetBulbTemperature": {"unit": "CELSIUS", "degrees": 2.6}, "precipitation": {"probability": {"type": "RAIN", "percent": 70}, "snowQpf": {"unit": "MILLIMETERS", "quantity": 0}, "qpf": {"unit": "MILLIMETERS", "quantity": 2.02}}, "airPressure": {"meanSeaLevelMillibars": 1022.52}, "wind": {"direction": {"cardinal": "NORTH", "degrees": 352}, "speed": {"unit": "KILOMETERS_PER_HOUR", "value": 11}, "gust": {"unit": "KILOMETERS_PER_HOUR", "value": 31}}, "visibility": {"unit": "KILOMETERS", "distance": 16}, "iceThickness": {"unit": "MILLIMETERS", "thickness": 0}, "isDaytime": true, "relativeHumidity": 56, "uvIndex": 1, "thunderstormProbability": 0, "cloudCover": 100}, {"interval": {"startTime": "2026-04-11T10:00:00Z", "endTime": "2026-04-11T11:00:00Z"}, "displayDateTime": {"year": 2026, "month": 4, "day": 11, "hours": 13, "minutes": 0, "seconds": 0, "nanos": 0, "utcOffset": "10800s"}, "weatherCondition": {"iconBaseUri": "https://maps.gstatic.com/weather/v1/showers", "description": {"text": "Rain", "languageCode": "en"}, "type": "RAIN"}, "temperature": {"unit": "CELSIUS", "degrees": 6.9}, "feelsLikeTemperature": {"unit": "CELSIUS", "degrees": 5}, "dewPoint": {"unit": "CELSIUS", "degrees": -2}, "heatIndex": {"unit": "CELSIUS", "degrees": 6.9}, "windChill": {"unit": "CELSIUS", "degrees": 5}, "wetBulbTemperature": {"unit": "CELSIUS", "degrees": 3.1}, "precipitation": {"probability": {"type": "RAIN", "percent": 70}, "snowQpf": {"unit": "MILLIMETERS", "quantity": 0}, "qpf": {"unit": "MILLIMETERS", "quantity": 2.02}}, "airPressure": {"meanSeaLevelMillibars": 1022.34}, "wind": {"direction": {"cardinal": "NORTH", "degrees": 352}, "speed": {"unit": "KILOMETERS_PER_HOUR", "value": 11}, "gust": {"unit": "KILOMETERS_PER_HOUR", "value": 31}}, "visibility": {"unit": "KILOMETERS", "distance": 16}, "iceThickness": {"unit": "MILLIMETERS", "thickness": 0}, "isDaytime": true, "relativeHumidity": 53, "uvIndex": 2, "thunderstormProbability": 10, "cloudCover": 100}, {"interval": {"startTime": "2026-04-11T11:00:00Z", "endTime": "2026-04-11T12:00:00Z"}, "displayDateTime": {"year": 2026, "month": 4, "day": 11, "hours": 14, "minutes": 0, "seconds": 0, "nanos": 0, "utcOffset": "10800s"}, "weatherCondition": {"iconBaseUri": "https://maps.gstatic.com/weather/v1/showers", "description": {"text": "Rain", "languageCode": "en"}, "type": "RAIN"}, "temperature": {"unit": "CELSIUS", "degrees": 7.5}, "feelsLikeTemperature": {"unit": "CELSIUS", "degrees": 6}, "dewPoint": {"unit": "CELSIUS", "degrees": -1.9}, "heatIndex": {"unit": "CELSIUS", "degrees": 7.5}, "windChill": {"unit": "CELSIUS", "degrees": 6}, "wetBulbTemperature": {"unit": "CELSIUS", "degrees": 3.3}, "precipitation": {"probability": {"type": "RAIN", "percent": 70}, "snowQpf": {"unit": "MILLIMETERS", "quantity": 0}, "qpf": {"unit": "MILLIMETERS", "quantity": 2.02}}, "airPressure": {"meanSeaLevelMillibars": 1021.99}, "wind": {"direction": {"cardinal": "NORTH", "degrees": 351}, "speed": {"unit": "KILOMETERS_PER_HOUR", "value": 11}, "gust": {"unit": "KILOMETERS_PER_HOUR", "value": 31}}, "visibility": {"unit": "KILOMETERS", "distance": 16}, "iceThickness": {"unit": "MILLIMETERS", "thickness": 0}, "isDaytime": true, "relativeHumidity": 51, "uvIndex": 2, "thunderstormProbability": 10, "cloudCover": 100}, {"interval": {"startTime": "2026-04-11T12:00:00Z", "endTime": "2026-04-11T13:00:00Z"}, "displayDateTime": {"year": 2026, "month": 4, "day": 11, "hours": 15, "minutes": 0, "seconds": 0, "nanos": 0, "utcOffset": "10800s"}, "weatherCondition": {"iconBaseUri": "https://maps.gstatic.com/weather/v1/showers", "description": {"text": "Rain", "languageCode": "en"}, "type": "RAIN"}, "temperature": {"unit": "CELSIUS", "degrees": 8}, "feelsLikeTemperature": {"unit": "CELSIUS", "degrees": 6}, "dewPoint": {"unit": "CELSIUS", "degrees": -1.9}, "heatIndex": {"unit": "CELSIUS", "degrees": 8}, "windChill": {"unit": "CELSIUS", "degrees": 6}, "wetBulbTemperature": {"unit": "CELSIUS", "degrees": 3.6}, "precipitation": {"probability": {"type": "RAIN", "percent": 70}, "snowQpf": {"unit": "MILLIMETERS", "quantity": 0}, "qpf": {"unit": "MILLIMETERS", "quantity": 2.02}}, "airPressure": {"meanSeaLevelMillibars": 1021.2}, "wind": {"direction": {"cardinal": "NORTH_NORTHWEST", "degrees": 345}, "speed": {"unit": "KILOMETERS_PER_HOUR", "value": 11}, "gust": {"unit": "KILOMETERS_PER_HOUR", "value": 34}}, "visibility": {"unit": "KILOMETERS", "distance": 16}, "iceThickness": {"unit": "MILLIMETERS", "thickness": 0}, "isDaytime": true, "relativeHumidity": 49, "uvIndex": 1, "thunderstormProbability": 10, "cloudCover": 100}, {"interval": {"startTime": "2026-04-11T13:00:00Z", "endTime": "2026-04-11T14:00:00Z"}, "displayDateTime": {"year": 2026, "month": 4, "day": 11, "hours": 16, "minutes": 0, "seconds": 0, "nanos": 0, "utcOffset": "10800s"}, "weatherCondition": {"iconBaseUri": "https://maps.gstatic.com/weather/v1/drizzle", "description": {"text": "Light rain", "languageCode": "en"}, "type": "LIGHT_RAIN"}, "temperature": {"unit": "CELSIUS", "degrees": 8.2}, "feelsLikeTemperature": {"unit": "CELSIUS", "degrees": 6}, "dewPoint": {"unit": "CELSIUS", "degrees": -2}, "heatIndex": {"unit": "CELSIUS", "degrees": 8.2}, "windChill": {"unit": "CELSIUS", "degrees": 6}, "wetBulbTemperature": {"unit": "CELSIUS", "degrees": 3.7}, "precipitation": {"probability": {"type": "RAIN", "percent": 35}, "snowQpf": {"unit": "MILLIMETERS", "quantity": 0}, "qpf": {"unit": "MILLIMETERS", "quantity": 0.49}}, "airPressure": {"meanSeaLevelMillibars": 1020.86}, "wind": {"direction": {"cardinal": "NORTH_NORTHWEST", "degrees": 345}, "speed": {"unit": "KILOMETERS_PER_HOUR", "value": 11}, "gust": {"unit": "KILOMETERS_PER_HOUR", "value": 32}}, "visibility": {"unit": "KILOMETERS", "distance": 16}, "iceThickness": {"unit": "MILLIMETERS", "thickness": 0}, "isDaytime": true, "relativeHumidity": 48, "uvIndex": 1, "thunderstormProbability": 10, "cloudCover": 98}, {"interval": {"startTime": "2026-04-11T14:00:00Z", "endTime": "2026-04-11T15:00:00Z"}, "displayDateTime": {"year": 2026, "month": 4, "day": 11, "hours": 17, "minutes": 0, "seconds": 0, "nanos": 0, "utcOffset": "10800s"}, "weatherCondition": {"iconBaseUri": "https://maps.gstatic.com/weather/v1/drizzle", "description": {"text": "Light rain", "languageCode": "en"}, "type": "LIGHT_RAIN"}, "temperature": {"unit": "CELSIUS", "degrees": 8.1}, "feelsLikeTemperature": {"unit": "CELSIUS", "degrees": 6}, "dewPoint": {"unit": "CELSIUS", "degrees": -2}, "heatIndex": {"unit": "CELSIUS", "degrees": 8.1}, "windChill": {"unit": "CELSIUS", "degrees": 6}, "wetBulbTemperature": {"unit": "CELSIUS", "degrees": 3.6}, "precipitation": {"probability": {"type": "RAIN", "percent": 35}, "snowQpf": {"unit": "MILLIMETERS", "quantity": 0}, "qpf": {"unit": "MILLIMETERS", "quantity": 0.49}}, "airPressure": {"meanSeaLevelMillibars": 1020.74}, "wind": {"direction": {"cardinal": "NORTH_NORTHWEST", "degrees": 346}, "speed": {"unit": "KILOMETERS_PER_HOUR", "value": 11}, "gust": {"unit": "KILOMETERS_PER_HOUR", "value": 31}}, "visibility": {"unit": "KILOMETERS", "distance": 16}, "iceThickness": {"unit": "MILLIMETERS", "thickness": 0}, "isDaytime": true, "relativeHumidity": 48, "uvIndex": 0, "thunderstormProbability": 10, "cloudCover": 96}, {"interval": {"startTime": "2026-04-11T15:00:00Z", "endTime": "2026-04-11T16:00:00Z"}, "displayDateTime": {"year": 2026, "month": 4, "day": 11, "hours": 18, "minutes": 0, "seconds": 0, "nanos": 0, "utcOffset": "10800s"}, "weatherCondition": {"iconBaseUri": "https://maps.gstatic.com/weather/v1/drizzle", "description": {"text": "Light rain", "languageCode": "en"}, "type": "LIGHT_RAIN"}, "temperature": {"unit": "CELSIUS", "degrees": 7.7}, "feelsLikeTemperature": {"unit": "CELSIUS", "degrees": 6}, "dewPoint": {"unit": "CELSIUS", "degrees": -2}, "heatIndex": {"unit": "CELSIUS", "degrees": 7.7}, "windChill": {"unit": "CELSIUS", "degrees": 6}, "wetBulbTemperature": {"unit": "CELSIUS", "degrees": 3.3}, "precipitation": {"probability": {"type": "RAIN", "percent": 35}, "snowQpf": {"unit": "MILLIMETERS", "quantity": 0}, "qpf": {"unit": "MILLIMETERS", "quantity": 0.49}}, "airPressure": {"meanSeaLevelMillibars": 1020.69}, "wind": {"direction": {"cardinal": "NORTH_NORTHWEST", "degrees": 344}, "speed": {"unit": "KILOMETERS_PER_HOUR", "value": 11}, "gust": {"unit": "KILOMETERS_PER_HOUR", "value": 27}}, "visibility": {"unit": "KILOMETERS", "distance": 16}, "iceThickness": {"unit": "MILLIMETERS", "thickness": 0}, "isDaytime": true, "relativeHumidity": 50, "uvIndex": 0, "thunderstormProbability": 10, "cloudCover": 95}, {"interval": {"startTime": "2026-04-11T16:00:00Z", "endTime": "2026-04-11T17:00:00Z"}, "displayDateTime": {"year": 2026, "month": 4, "day": 11, "hours": 19, "minutes": 0, "seconds": 0, "nanos": 0, "utcOffset": "10800s"}, "weatherCondition": {"iconBaseUri": "https://maps.gstatic.com/weather/v1/drizzle", "description": {"text": "Light rain", "languageCode": "en"}, "type": "LIGHT_RAIN"}, "temperature": {"unit": "CELSIUS", "degrees": 6.9}, "feelsLikeTemperature": {"unit": "CELSIUS", "degrees": 5}, "dewPoint": {"unit": "CELSIUS", "degrees": -2}, "heatIndex": {"unit": "CELSIUS", "degrees": 6.9}, "windChill": {"unit": "CELSIUS", "degrees": 5}, "wetBulbTemperature": {"unit": "CELSIUS", "degrees": 3}, "precipitation": {"probability": {"type": "RAIN", "percent": 35}, "snowQpf": {"unit": "MILLIMETERS", "quantity": 0}, "qpf": {"unit": "MILLIMETERS", "quantity": 0.49}}, "airPressure": {"meanSeaLevelMillibars": 1020.84}, "wind": {"direction": {"cardinal": "NORTH_NORTHWEST", "degrees": 340}, "speed": {"unit": "KILOMETERS_PER_HOUR", "value": 10}, "gust": {"unit": "KILOMETERS_PER_HOUR", "value": 21}}, "visibility": {"unit": "KILOMETERS", "distance": 16}, "iceThickness": {"unit": "MILLIMETERS", "thickness": 0}, "isDaytime": true, "relativeHumidity": 53, "uvIndex": 0, "thunderstormProbability": 10, "cloudCover": 96}, {"interval": {"startTime": "2026-04-11T17:00:00Z", "endTime": "2026-04-11T18:00:00Z"}, "displayDateTime": {"year": 2026, "month": 4, "day": 11, "hours": 20, "minutes": 0, "seconds": 0, "nanos": 0, "utcOffset": "10800s"}, "weatherCondition": {"iconBaseUri": "https://maps.gstatic.com/weather/v1/drizzle", "description": {"text": "Light rain", "languageCode": "en"}, "type": "LIGHT_RAIN"}, "temperature": {"unit": "CELSIUS", "degrees": 5.1}, "feelsLikeTemperature": {"unit": "CELSIUS", "degrees": 3}, "dewPoint": {"unit": "CELSIUS", "degrees": -2}, "heatIndex": {"unit": "CELSIUS", "degrees": 5.1}, "windChill": {"unit": "CELSIUS", "degrees": 3}, "wetBulbTemperature": {"unit": "CELSIUS", "degrees": 2}, "precipitation": {"probability": {"type": "RAIN", "percent": 35}, "snowQpf": {"unit": "MILLIMETERS", "quantity": 0}, "qpf": {"unit": "MILLIMETERS", "quantity": 0.49}}, "airPressure": {"meanSeaLevelMillibars": 1021.13}, "wind": {"direction": {"cardinal": "NORTH_NORTHWEST", "degrees": 336}, "speed": {"unit": "KILOMETERS_PER_HOUR", "value": 6}, "gust": {"unit": "KILOMETERS_PER_HOUR", "value": 16}}, "visibility": {"unit": "KILOMETERS", "distance": 16}, "iceThickness": {"unit": "MILLIMETERS", "thickness": 0}, "isDaytime": true, "relativeHumidity": 60, "uvIndex": 0, "thunderstormProbability": 10, "cloudCover": 98}, {"interval": {"startTime": "2026-04-11T18:00:00Z", "endTime": "2026-04-11T19:00:00Z"}, "displayDateTime": {"year": 2026, "month": 4, "day": 11, "hours": 21, "minutes": 0, "seconds": 0, "nanos": 0, "utcOffset": "10800s"}, "weatherCondition": {"iconBaseUri": "https://maps.gstatic.com/weather/v1/drizzle", "description": {"text": "Light rain", "languageCode": "en"}, "type": "LIGHT_RAIN"}, "temperature": {"unit": "CELSIUS", "degrees": 4.3}, "feelsLikeTemperature": {"unit": "CELSIUS", "degrees": 3}, "dewPoint": {"unit": "CELSIUS", "degrees": -2}, "heatIndex": {"unit": "CELSIUS", "degrees": 4.3}, "windChill": {"unit": "CELSIUS", "degrees": 3}, "wetBulbTemperature": {"unit": "CELSIUS", "degrees": 1.6}, "precipitation": {"probability": {"type": "RAIN", "percent": 35}, "snowQpf": {"unit": "MILLIMETERS", "quantity": 0}, "qpf": {"unit": "MILLIMETERS", "quantity": 0.49}}, "airPressure": {"meanSeaLevelMillibars": 1021.1}, "wind": {"direction": {"cardinal": "NORTH_NORTHWEST", "degrees": 338}, "speed": {"unit": "KILOMETERS_PER_HOUR", "value": 6}, "gust": {"unit": "KILOMETERS_PER_HOUR", "value": 13}}, "visibility": {"unit": "KILOMETERS", "distance": 16}, "iceThickness": {"unit": "MILLIMETERS", "thickness": 0}, "isDaytime": false, "relativeHumidity": 63, "uvIndex": 0, "thunderstormProbability": 0, "cloudCover": 100}, {"interval": {"startTime": "2026-04-11T19:00:00Z", "endTime": "2026-04-11T20:00:00Z"}, "displayDateTime": {"year": 2026, "month": 4, "day": 11, "hours": 22, "minutes": 0, "seconds": 0, "nanos": 0, "utcOffset": "10800s"}, "weatherCondition": {"iconBaseUri": "https://maps.gstatic.com/weather/v1/scattered_snow", "description": {"text": "Snow showers", "languageCode": "en"}, "type": "SNOW_SHOWERS"}, "temperature": {"unit": "CELSIUS", "degrees": 3.7}, "feelsLikeTemperature": {"unit": "CELSIUS", "degrees": 2}, "dewPoint": {"unit": "CELSIUS", "degrees": -2.2}, "heatIndex": {"unit": "CELSIUS", "degrees": 3.7}, "windChill": {"unit": "CELSIUS", "degrees": 2}, "wetBulbTemperature": {"unit": "CELSIUS", "degrees": 1.2}, "precipitation": {"probability": {"type": "SNOW", "percent": 35}, "snowQpf": {"unit": "MILLIMETERS", "quantity": 3.24}, "qpf": {"unit": "MILLIMETERS", "quantity": 0.24}}, "airPressure": {"meanSeaLevelMillibars": 1021.52}, "wind": {"direction": {"cardinal": "NORTH", "degrees": 354}, "speed": {"unit": "KILOMETERS_PER_HOUR", "value": 5}, "gust": {"unit": "KILOMETERS_PER_HOUR", "value": 13}}, "visibility": {"unit": "KILOMETERS", "distance": 16}, "iceThickness": {"unit": "MILLIMETERS", "thickness": 0}, "isDaytime": false, "relativeHumidity": 65, "uvIndex": 0, "thunderstormProbability": 0, "cloudCover": 99}, {"interval": {"startTime": "2026-04-11T20:00:00Z", "endTime": "2026-04-11T21:00:00Z"}, "displayDateTime": {"year": 2026, "month": 4, "day": 11, "hours": 23, "minutes": 0, "seconds": 0, "nanos": 0, "utcOffset": "10800s"}, "weatherCondition": {"iconBaseUri": "https://maps.gstatic.com/weather/v1/scattered_snow", "description": {"text": "Snow showers", "languageCode": "en"}, "type": "SNOW_SHOWERS"}, "temperature": {"unit": "CELSIUS", "degrees": 3.1}, "feelsLikeTemperature": {"unit": "CELSIUS", "degrees": 2}, "dewPoint": {"unit": "CELSIUS", "degrees": -2.4}, "heatIndex": {"unit": "CELSIUS", "degrees": 3.1}, "windChill": {"unit": "CELSIUS", "degrees": 2}, "wetBulbTemperature": {"unit": "CELSIUS", "degrees": 0.8}, "precipitation": {"probability": {"type": "SNOW", "percent": 35}, "snowQpf": {"unit": "MILLIMETERS", "quantity": 3.26}, "qpf": {"unit": "MILLIMETERS", "quantity": 0.24}}, "airPressure": {"meanSeaLevelMillibars": 1021.59}, "wind": {"direction": {"cardinal": "NORTH_NORTHEAST", "degrees": 18}, "speed": {"unit": "KILOMETERS_PER_HOUR", "value": 5}, "gust": {"unit": "KILOMETERS_PER_HOUR", "value": 11}}, "visibility": {"unit": "KILOMETERS", "distance": 16}, "iceThickness": {"unit": "MILLIMETERS", "thickness": 0}, "isDaytime": false, "relativeHumidity": 67, "uvIndex": 0, "thunderstormProbability": 0, "cloudCover": 99}], "timeZone": {"id": "Europe/Bucharest", "version": ""}, "nextPageToken": "ChcKEglrf2d79I5GQBGKHY1D_eY1QBDwARCoARioASIMCMH-xc4GEOH-45YBKhBFdXJvcGUvQnVjaGFyZXN0"}